verilog/wbuf/wbuf_send_old.v
module wbuf_send(
	input wire CLK, 
	input wire RSTL,
  input wire WBUF_SEND,
	output reg [15:0] RADDRX, //SRAMのどのアドレスか
	output reg RCEBX, //SRAMのデータを取り出す処理
	output reg WBUF_EN, //PBのデータ受け入れ開始
	output reg [5:0] WBUF_EN_CTRL //PBの列指定
	);

	reg [15:0] pc;
	reg [2:0] cnt;
	reg [7:0] counter0;

	
	//counter0
  always @(posedge CLK or negedge RSTL)  begin
		if (!RSTL) begin
			counter0 <= 8'd0;
    end else if(WBUF_SEND) begin
			counter0 <= 8'd32;
			RCEBX <= 0;
		end else if(counter0 != 0 && cnt == 3'b100) //１ループを4サイクル設定
			counter0 <= counter0 - 1;
	end

  //RCEBX
  always @(posedge CLK or negedge RSTL) begin
		if (!RSTL)			
			RCEBX <= 1;
		else if(counter0)
      RCEBX <= 0;
		else
			RCEBX <= 1;
	end

  //WBUF_EN
  always @(posedge CLK or negedge RSTL) begin
		if (!RSTL)			
			WBUF_EN <= 3'b000;
		else if(counter0)
      WBUF_EN <= 1;
		else
			WBUF_EN <= 0;
	end

	//cnt:アドレス用カウンタ(4サイクル)
  always @(posedge CLK or negedge RSTL) begin
		if (!RSTL)			
			cnt <= 3'b000;
		else if(counter0) begin
			if(cnt == 3'b100) begin
				if(counter0 == 16'd1) begin
					cnt <= 3'b000;
					WBUF_EN <= 0;
				end else
					cnt <= 3'b001;
			end else
        cnt <= cnt + 1;
		end else
			cnt <= 3'b000;
	end

	//RADDRX
	always @(posedge CLK or negedge RSTL) begin
		if (!RSTL)			
			RADDRX <= 16'd0;
		else if(counter0) begin
      if(cnt == 3'b100 && counter0 == 1)
        RADDRX <= RADDRX;
      else
			  RADDRX <= RADDRX + 16'b1;
    end
	end

	//WBUF_EN_CTRL
	always@ (posedge CLK or negedge RSTL) begin
		if (!RSTL)       
			WBUF_EN_CTRL <= 6'b0;
		else if(counter0 != 1 && cnt == 3'b100)
			WBUF_EN_CTRL <= WBUF_EN_CTRL + 6'b1;
	end


endmodule

verilog/wbuf/wbuf_send_test.v
module wbuf_send_test;
  reg CLK, RSTL, WBUF_SEND;
  wire [15:0] RADDRX;
  wire [5:0] WBUF_EN_CTRL;
  wire WBUF_EN, RCEBX;

  wbuf_send wbuf_send_instance(
    .CLK(CLK),
    .RSTL(RSTL),
    .WBUF_SEND(WBUF_SEND),
    .RADDRX(RADDRX),
    .RCEBX(RCEBX),
    .WBUF_EN(WBUF_EN),
    .WBUF_EN_CTRL(WBUF_EN_CTRL)
  );

  parameter step = 10;

  initial begin
    CLK = 0;
    forever #(step) CLK = ~CLK;
  end

  initial begin
    RSTL = 0;
    WBUF_SEND = 0;
    #(step*3)
    RSTL = 1;
    WBUF_SEND = 1;

    #(step*2)
    WBUF_SEND = 0;
  end

  initial begin
    #(step*500) $finish();
  end
  
  initial begin
    $dumpfile("wbuf_send_test.vcd");
    $dumpvars(0, wbuf_send_instance);
  end

endmodule

verilog/wbuf/wbuf_send_test.vcd
$date
	Thu Jan 14 15:25:04 2021
$end
$version
	Icarus Verilog
$end
$timescale
	1s
$end
$scope module wbuf_send_test $end
$scope module wbuf_send_instance $end
$var wire 1 ! CLK $end
$var wire 1 " RSTL $end
$var wire 1 # WBUF_SEND $end
$var reg 16 $ RADDRX [15:0] $end
$var reg 1 % RCEBX $end
$var reg 1 & WBUF_EN $end
$var reg 6 ' WBUF_EN_CTRL [5:0] $end
$var reg 3 ( cnt [2:0] $end
$var reg 8 ) counter0 [7:0] $end
$upscope $end
$upscope $end
$enddefinitions $end
#0
$dumpvars
b0 )
b0 (
b0 '
0&
1%
b0 $
0#
0"
0!
$end
#10
1!
#20
0!
#30
0%
b100000 )
1!
1#
1"
#40
0!
#50
b1 $
b1 (
1&
1!
0#
#60
0!
#70
b10 (
b10 $
1!
#80
0!
#90
b11 $
b11 (
1!
#100
0!
#110
b100 (
b100 $
1!
#120
0!
#130
b1 '
b101 $
b1 (
b11111 )
1!
#140
0!
#150
b10 (
b110 $
1!
#160
0!
#170
b111 $
b11 (
1!
#180
0!
#190
b100 (
b1000 $
1!
#200
0!
#210
b10 '
b1001 $
b1 (
b11110 )
1!
#220
0!
#230
b10 (
b1010 $
1!
#240
0!
#250
b1011 $
b11 (
1!
#260
0!
#270
b100 (
b1100 $
1!
#280
0!
#290
b11 '
b1101 $
b1 (
b11101 )
1!
#300
0!
#310
b10 (
b1110 $
1!
#320
0!
#330
b1111 $
b11 (
1!
#340
0!
#350
b100 (
b10000 $
1!
#360
0!
#370
b100 '
b10001 $
b1 (
b11100 )
1!
#380
0!
#390
b10 (
b10010 $
1!
#400
0!
#410
b10011 $
b11 (
1!
#420
0!
#430
b100 (
b10100 $
1!
#440
0!
#450
b101 '
b10101 $
b1 (
b11011 )
1!
#460
0!
#470
b10 (
b10110 $
1!
#480
0!
#490
b10111 $
b11 (
1!
#500
0!
#510
b100 (
b11000 $
1!
#520
0!
#530
b110 '
b11001 $
b1 (
b11010 )
1!
#540
0!
#550
b10 (
b11010 $
1!
#560
0!
#570
b11011 $
b11 (
1!
#580
0!
#590
b100 (
b11100 $
1!
#600
0!
#610
b111 '
b11101 $
b1 (
b11001 )
1!
#620
0!
#630
b10 (
b11110 $
1!
#640
0!
#650
b11111 $
b11 (
1!
#660
0!
#670
b100 (
b100000 $
1!
#680
0!
#690
b1000 '
b100001 $
b1 (
b11000 )
1!
#700
0!
#710
b10 (
b100010 $
1!
#720
0!
#730
b100011 $
b11 (
1!
#740
0!
#750
b100 (
b100100 $
1!
#760
0!
#770
b1001 '
b100101 $
b1 (
b10111 )
1!
#780
0!
#790
b10 (
b100110 $
1!
#800
0!
#810
b100111 $
b11 (
1!
#820
0!
#830
b100 (
b101000 $
1!
#840
0!
#850
b1010 '
b101001 $
b1 (
b10110 )
1!
#860
0!
#870
b10 (
b101010 $
1!
#880
0!
#890
b101011 $
b11 (
1!
#900
0!
#910
b100 (
b101100 $
1!
#920
0!
#930
b1011 '
b101101 $
b1 (
b10101 )
1!
#940
0!
#950
b10 (
b101110 $
1!
#960
0!
#970
b101111 $
b11 (
1!
#980
0!
#990
b100 (
b110000 $
1!
#1000
0!
#1010
b1100 '
b110001 $
b1 (
b10100 )
1!
#1020
0!
#1030
b10 (
b110010 $
1!
#1040
0!
#1050
b110011 $
b11 (
1!
#1060
0!
#1070
b100 (
b110100 $
1!
#1080
0!
#1090
b1101 '
b110101 $
b1 (
b10011 )
1!
#1100
0!
#1110
b10 (
b110110 $
1!
#1120
0!
#1130
b110111 $
b11 (
1!
#1140
0!
#1150
b100 (
b111000 $
1!
#1160
0!
#1170
b1110 '
b111001 $
b1 (
b10010 )
1!
#1180
0!
#1190
b10 (
b111010 $
1!
#1200
0!
#1210
b111011 $
b11 (
1!
#1220
0!
#1230
b100 (
b111100 $
1!
#1240
0!
#1250
b1111 '
b111101 $
b1 (
b10001 )
1!
#1260
0!
#1270
b10 (
b111110 $
1!
#1280
0!
#1290
b111111 $
b11 (
1!
#1300
0!
#1310
b100 (
b1000000 $
1!
#1320
0!
#1330
b10000 '
b1000001 $
b1 (
b10000 )
1!
#1340
0!
#1350
b10 (
b1000010 $
1!
#1360
0!
#1370
b1000011 $
b11 (
1!
#1380
0!
#1390
b100 (
b1000100 $
1!
#1400
0!
#1410
b10001 '
b1000101 $
b1 (
b1111 )
1!
#1420
0!
#1430
b10 (
b1000110 $
1!
#1440
0!
#1450
b1000111 $
b11 (
1!
#1460
0!
#1470
b100 (
b1001000 $
1!
#1480
0!
#1490
b10010 '
b1001001 $
b1 (
b1110 )
1!
#1500
0!
#1510
b10 (
b1001010 $
1!
#1520
0!
#1530
b1001011 $
b11 (
1!
#1540
0!
#1550
b100 (
b1001100 $
1!
#1560
0!
#1570
b10011 '
b1001101 $
b1 (
b1101 )
1!
#1580
0!
#1590
b10 (
b1001110 $
1!
#1600
0!
#1610
b1001111 $
b11 (
1!
#1620
0!
#1630
b100 (
b1010000 $
1!
#1640
0!
#1650
b10100 '
b1010001 $
b1 (
b1100 )
1!
#1660
0!
#1670
b10 (
b1010010 $
1!
#1680
0!
#1690
b1010011 $
b11 (
1!
#1700
0!
#1710
b100 (
b1010100 $
1!
#1720
0!
#1730
b10101 '
b1010101 $
b1 (
b1011 )
1!
#1740
0!
#1750
b10 (
b1010110 $
1!
#1760
0!
#1770
b1010111 $
b11 (
1!
#1780
0!
#1790
b100 (
b1011000 $
1!
#1800
0!
#1810
b10110 '
b1011001 $
b1 (
b1010 )
1!
#1820
0!
#1830
b10 (
b1011010 $
1!
#1840
0!
#1850
b1011011 $
b11 (
1!
#1860
0!
#1870
b100 (
b1011100 $
1!
#1880
0!
#1890
b10111 '
b1011101 $
b1 (
b1001 )
1!
#1900
0!
#1910
b10 (
b1011110 $
1!
#1920
0!
#1930
b1011111 $
b11 (
1!
#1940
0!
#1950
b100 (
b1100000 $
1!
#1960
0!
#1970
b11000 '
b1100001 $
b1 (
b1000 )
1!
#1980
0!
#1990
b10 (
b1100010 $
1!
#2000
0!
#2010
b1100011 $
b11 (
1!
#2020
0!
#2030
b100 (
b1100100 $
1!
#2040
0!
#2050
b11001 '
b1100101 $
b1 (
b111 )
1!
#2060
0!
#2070
b10 (
b1100110 $
1!
#2080
0!
#2090
b1100111 $
b11 (
1!
#2100
0!
#2110
b100 (
b1101000 $
1!
#2120
0!
#2130
b11010 '
b1101001 $
b1 (
b110 )
1!
#2140
0!
#2150
b10 (
b1101010 $
1!
#2160
0!
#2170
b1101011 $
b11 (
1!
#2180
0!
#2190
b100 (
b1101100 $
1!
#2200
0!
#2210
b11011 '
b1101101 $
b1 (
b101 )
1!
#2220
0!
#2230
b10 (
b1101110 $
1!
#2240
0!
#2250
b1101111 $
b11 (
1!
#2260
0!
#2270
b100 (
b1110000 $
1!
#2280
0!
#2290
b11100 '
b1110001 $
b1 (
b100 )
1!
#2300
0!
#2310
b10 (
b1110010 $
1!
#2320
0!
#2330
b1110011 $
b11 (
1!
#2340
0!
#2350
b100 (
b1110100 $
1!
#2360
0!
#2370
b11101 '
b1110101 $
b1 (
b11 )
1!
#2380
0!
#2390
b10 (
b1110110 $
1!
#2400
0!
#2410
b1110111 $
b11 (
1!
#2420
0!
#2430
b100 (
b1111000 $
1!
#2440
0!
#2450
b11110 '
b1111001 $
b1 (
b10 )
1!
#2460
0!
#2470
b10 (
b1111010 $
1!
#2480
0!
#2490
b1111011 $
b11 (
1!
#2500
0!
#2510
b100 (
b1111100 $
1!
#2520
0!
#2530
b11111 '
b1111101 $
b1 (
b1 )
1!
#2540
0!
#2550
b10 (
b1111110 $
1!
#2560
0!
#2570
b1111111 $
b11 (
1!
#2580
0!
#2590
b100 (
b10000000 $
1!
#2600
0!
#2610
0&
b0 (
b0 )
1!
#2620
0!
#2630
1%
1!
