verilog/pra/wbuf_send.v
module wbuf_send(
	input wire CLK, 
	input wire RSTL,
	input wire WBUF_SEND, //開始スイッチ
	input wire [15:0] addr, //SRAMの開始アドレス
	input wire [15:0] loop, //ループ回数
	input wire [5:0] wbuf_ec, //PBの列指定
	output reg [2:0] cnt, //#のサイクル(4周期)
	output reg [15:0] RADDRX, //_WEの処理の数値
	output reg RCEBX, //データを取り出す処理
	output reg WBUF_EN, //0：PB受け入れ中止, 1：PB受け入れ開始
	output reg [5:0] WBUF_EN_CTRL, //PBの列指定
	output reg [15:0] COUNTER0 //ループ回数
	);

	
	//ループ用カウンター
  always @(posedge CLK or negedge RSTL)  begin
		if (!RSTL)			
			COUNTER0 <= 16'd0;
		else if(WBUF_SEND) begin
			COUNTER0 <= loop;
			RCEBX <= 0;
			WBUF_EN <= 1;
		end else if(COUNTER0 != 0 && cnt == 3'b100) //１ループを4サイクル設定
			COUNTER0 <= COUNTER0 - 1;
	end

	//ループの中身用カウンタ(4サイクル)
  always @(posedge CLK or negedge RSTL) begin
		if (!RSTL)			
			cnt <= 3'b000;
		else if(COUNTER0) begin
			if(cnt == 3'b100) begin
				if(COUNTER0 == 16'd1) begin
					cnt <= 3'b000;
					WBUF_EN <= 0;
				end else
					cnt <= 3'b001;
			end else
        cnt <= cnt + 1;
		end else
			cnt <= 3'b000;
	end

	//RADDRX
	always @(cnt) begin
		if (!RSTL)			
			RADDRX <= 16'd0;
		else if(WBUF_SEND)
			RADDRX <= addr;
		else if(COUNTER0)
			RADDRX <= RADDRX + 16'b1;
	end

	//WBUF_EN_CTRL
	always@ (cnt) begin
		if (!RSTL)       
			WBUF_EN_CTRL <= 6'b0;
		else if(WBUF_SEND) 
			WBUF_EN_CTRL <= wbuf_ec;
		else if(COUNTER0) begin
			WBUF_EN_CTRL <= WBUF_EN_CTRL + 6'b1;
		end
	end


endmodule

verilog/pra/wbuf_send_test.v
module wbuf_send_test;
  reg CLK, RSTL, WBUF_SEND;
  reg [15:0] addr;
  reg [15:0] loop;
  reg [5:0] wbuf_ec;
  wire [2:0] cnt;
  wire [15:0] RADDRX;
  wire [5:0] WBUF_EN_CTRL;
  wire [15:0] COUNTER0;
  wire WBUF_EN, RCEBX;

  wbuf_send wbuf_send_instance(
    .CLK(CLK),
    .RSTL(RSTL),
    .WBUF_SEND(WBUF_SEND),
    .addr(addr),
    .loop(loop),
    .wbuf_ec(wbuf_ec),
    .cnt(cnt),
    .COUNTER0(COUNTER0),
    .RCEBX(RCEBX),
    .WBUF_EN(WBUF_EN),
    .WBUF_EN_CTRL(WBUF_EN_CTRL)
  );

  parameter step = 10;

  initial begin
    CLK = 0;
    forever #(step) CLK = ~CLK;
  end

  initial begin
    RSTL = 0;
    WBUF_SEND = 0;
    addr = 16'b0;
    wbuf_ec = 6'b0;
    loop = 5;
    #(step*3)
    RSTL = 1;
    WBUF_SEND = 1;

    #step
    WBUF_SEND = 0;
  end

  initial begin
    #(step*100) $finish();
  end
  
  initial begin
    $dumpfile("wbuf_send_test.vcd");
    $dumpvars(0, wbuf_send_instance);
  end

endmodule

verilog/pra/wbuf_send_test.vcd
$date
	Mon Oct 26 17:46:10 2020
$end
$version
	Icarus Verilog
$end
$timescale
	1s
$end
$scope module wbuf_send_test $end
$scope module wbuf_send_instance $end
$var wire 1 ! CLK $end
$var wire 1 " RSTL $end
$var wire 1 # WBUF_SEND $end
$var wire 16 $ addr [15:0] $end
$var wire 16 % loop [15:0] $end
$var wire 6 & wbuf_ec [5:0] $end
$var reg 16 ' COUNTER0 [15:0] $end
$var reg 16 ( RADDRX [15:0] $end
$var reg 1 ) RCEBX $end
$var reg 1 * WBUF_EN $end
$var reg 6 + WBUF_EN_CTRL [5:0] $end
$var reg 3 , cnt [2:0] $end
$upscope $end
$upscope $end
$enddefinitions $end
#0
$dumpvars
b0 ,
b0 +
x*
x)
b0 (
b0 '
b0 &
b101 %
b0 $
0#
0"
0!
$end
#10
1!
#20
0!
#30
1*
0)
b101 '
1!
1#
1"
#40
0!
0#
#50
b1 (
b1 +
b1 ,
1!
#60
0!
#70
b10 +
b10 (
b10 ,
1!
#80
0!
#90
b11 (
b11 +
b11 ,
1!
#100
0!
#110
b100 +
b100 (
b100 ,
1!
#120
0!
#130
b101 (
b101 +
b1 ,
b100 '
1!
#140
0!
#150
b110 +
b110 (
b10 ,
1!
#160
0!
#170
b111 (
b111 +
b11 ,
1!
#180
0!
#190
b1000 +
b1000 (
b100 ,
1!
#200
0!
#210
b1001 (
b1001 +
b1 ,
b11 '
1!
#220
0!
#230
b1010 +
b1010 (
b10 ,
1!
#240
0!
#250
b1011 (
b1011 +
b11 ,
1!
#260
0!
#270
b1100 +
b1100 (
b100 ,
1!
#280
0!
#290
b1101 (
b1101 +
b1 ,
b10 '
1!
#300
0!
#310
b1110 +
b1110 (
b10 ,
1!
#320
0!
#330
b1111 (
b1111 +
b11 ,
1!
#340
0!
#350
b10000 +
b10000 (
b100 ,
1!
#360
0!
#370
b10001 (
b10001 +
b1 ,
b1 '
1!
#380
0!
#390
b10010 +
b10010 (
b10 ,
1!
#400
0!
#410
b10011 (
b10011 +
b11 ,
1!
#420
0!
#430
b10100 +
b10100 (
b100 ,
1!
#440
0!
#450
0*
b0 ,
b0 '
1!
