verilog/FIFO.v
//---------------------------------------
//module FIFO 
//                    made by Ryohei.K
//---------------------------------------

`default_nettype none
`define FIFO_D 4
module FIFO(
  input wire        clk,
  input wire        n_rst,
  input wire  [DATA_WIDTH - 1:0] din,
  input wire        rd_en,
  input wire        wr_en,
  output reg        empty,
  output reg        full,
  output reg  [DATA_WIDTH - 1:0] dout
);
  parameter DATA_WIDTH   = 8;
  parameter FIFO_DEPTH   = 4;

  reg [0:2**FIFO_DEPTH]  rd_addr;
  reg [0:2**FIFO_DEPTH]  wr_addr;
  reg [DATA_WIDTH - 1:0]  data[0:2**FIFO_DEPTH - 1];

//FIFO
  always @(posedge clk)begin
    if(wr_en & !full)data[wr_addr] <= din;
    if(rd_en & !empty)dout <= data[rd_addr];
  end

//Write address
  always @(posedge clk or posedge n_rst)begin
    if(n_rst)begin
      wr_addr <= 0;
    end else begin
      if(wr_en == 1'b1 & full == 1'b0)begin
        if(wr_addr == `FIFO_D'b1111)begin
          wr_addr <= 0;
        end else begin
          wr_addr <= wr_addr + 1'b1;
        end
      end
    end
  end

//Read address
    always @(posedge clk or posedge n_rst)begin
      if(n_rst)begin
        rd_addr <= 0;
      end else begin
        if(rd_en)begin
          if(rd_addr == `FIFO_D'b1111)begin
            rd_addr <= 0;
          end else begin
            rd_addr <= rd_addr + 1'b1;
          end
        end
      end
    end

//Full flag
  always @(posedge clk or posedge n_rst)begin
    if(n_rst)begin
      full <= 0;
    end else begin
      if( wr_addr == `FIFO_D'b1111 & wr_en == 1 & rd_en == 0)begin
        full <= 1;
      end else if(full == 1 &rd_en == 1)begin
        full <= 0;
      end
    end
  end

  //Empty flag
  always @(posedge clk or posedge n_rst)begin
    if(n_rst)begin
      empty <= 1;
    end else begin
      if(wr_en)begin
        empty <= 0;
      end
    end
  end
endmodule

verilog/pra/FIFO_bench.v
`timescale 1ps/1ps
module FIFO_bench();

  parameter DATA_WIDTH   = 8;
  parameter FIFO_DEPTH   = 4;
  reg clk,n_rst,rd_en,wr_en;
  reg  [DATA_WIDTH - 1:0]  din;
  wire [DATA_WIDTH - 1:0]  dout;

  FIFO #(.FIFO_DEPTH(FIFO_DEPTH))u0(
    .clk(clk),
    .n_rst(n_rst),
    .rd_en(rd_en),
    .wr_en(wr_en),
    .din(din),
    .dout(dout)
  );

  initial begin
    n_rst = 1;
    #10 n_rst = ~n_rst;
  end

  initial begin
    clk = 0;
    rd_en = 0;
    forever #10 clk = ~clk;
  end

  initial begin 
    #10 wr_en = 1;
        din = 1;
    #10 wr_en = ~wr_en;
    #10 wr_en = 1;
        din = 2;
    #10 wr_en = ~wr_en;
    #10 wr_en = 1;
        din = 3;
    #10 wr_en = ~wr_en;
    #10 wr_en = 1;
        din = 4;
    #10 wr_en = ~wr_en;
    #10 wr_en = 1;
        din = 5;
    #10 wr_en = ~wr_en;
    #10 wr_en = 1;
        din = 6;
    #10 wr_en = ~wr_en;
    #10 wr_en = 1;
        din = 7;
    #10 wr_en = ~wr_en;
    #10 wr_en = 1;
        din = 8;
    #10 wr_en = ~wr_en;
    #10 wr_en = 1;
        din = 9;
    #10 wr_en = ~wr_en;
    #10 wr_en = 1;
        din = 10;
    #10 wr_en = ~wr_en;
    #10 rd_en = 1'b1;
    #10 rd_en = ~rd_en;
    #10 rd_en = 1'b1;
    #10 rd_en = ~rd_en;
    #10 rd_en = 1'b1;
    #10 rd_en = ~rd_en;
    #10 rd_en = 1'b1;
    #10 rd_en = ~rd_en;
    #10 rd_en = 1'b1;
    #10 rd_en = ~rd_en;
  end
integer i;
  initial begin
    $dumpfile("FIFO.vcd");
    $dumpvars(0, FIFO_bench);
    for(i = 0;i < 2**FIFO_DEPTH;i++)
      $dumpvars(1,u0.data[i]);
    $monitor ("%t: clk = %b r_data = %b", $time, clk,dout);
  end

  initial begin
    #500 $finish();
  end

endmodule

verilog/FIFO.vcd
$date
	Tue Sep 29 15:55:02 2020
$end
$version
	Icarus Verilog
$end
$timescale
	1ps
$end
$scope module FIFO_bench $end
$var wire 8 ! dout [7:0] $end
$var reg 1 " clk $end
$var reg 8 # din [7:0] $end
$var reg 1 $ n_rst $end
$var reg 1 % rd_en $end
$var reg 1 & wr_en $end
$var integer 32 ' i [31:0] $end
$scope module u0 $end
$var wire 1 " clk $end
$var wire 8 ( din [7:0] $end
$var wire 1 $ n_rst $end
$var wire 1 % rd_en $end
$var wire 1 & wr_en $end
$var reg 8 ) dout [7:0] $end
$var reg 1 * empty $end
$var reg 1 + full $end
$var reg 17 , rd_addr [0:16] $end
$var reg 17 - wr_addr [0:16] $end
$upscope $end
$upscope $end
$scope module FIFO_bench $end
$scope module u0 $end
$var reg 8 . \data[0] [7:0] $end
$upscope $end
$upscope $end
$scope module FIFO_bench $end
$scope module u0 $end
$var reg 8 / \data[1] [7:0] $end
$upscope $end
$upscope $end
$scope module FIFO_bench $end
$scope module u0 $end
$var reg 8 0 \data[2] [7:0] $end
$upscope $end
$upscope $end
$scope module FIFO_bench $end
$scope module u0 $end
$var reg 8 1 \data[3] [7:0] $end
$upscope $end
$upscope $end
$scope module FIFO_bench $end
$scope module u0 $end
$var reg 8 2 \data[4] [7:0] $end
$upscope $end
$upscope $end
$scope module FIFO_bench $end
$scope module u0 $end
$var reg 8 3 \data[5] [7:0] $end
$upscope $end
$upscope $end
$scope module FIFO_bench $end
$scope module u0 $end
$var reg 8 4 \data[6] [7:0] $end
$upscope $end
$upscope $end
$scope module FIFO_bench $end
$scope module u0 $end
$var reg 8 5 \data[7] [7:0] $end
$upscope $end
$upscope $end
$scope module FIFO_bench $end
$scope module u0 $end
$var reg 8 6 \data[8] [7:0] $end
$upscope $end
$upscope $end
$scope module FIFO_bench $end
$scope module u0 $end
$var reg 8 7 \data[9] [7:0] $end
$upscope $end
$upscope $end
$scope module FIFO_bench $end
$scope module u0 $end
$var reg 8 8 \data[10] [7:0] $end
$upscope $end
$upscope $end
$scope module FIFO_bench $end
$scope module u0 $end
$var reg 8 9 \data[11] [7:0] $end
$upscope $end
$upscope $end
$scope module FIFO_bench $end
$scope module u0 $end
$var reg 8 : \data[12] [7:0] $end
$upscope $end
$upscope $end
$scope module FIFO_bench $end
$scope module u0 $end
$var reg 8 ; \data[13] [7:0] $end
$upscope $end
$upscope $end
$scope module FIFO_bench $end
$scope module u0 $end
$var reg 8 < \data[14] [7:0] $end
$upscope $end
$upscope $end
$scope module FIFO_bench $end
$scope module u0 $end
$var reg 8 = \data[15] [7:0] $end
$upscope $end
$upscope $end
$enddefinitions $end
#0
$dumpvars
bx =
bx <
bx ;
bx :
bx 9
bx 8
bx 7
bx 6
bx 5
bx 4
bx 3
bx 2
bx 1
bx 0
bx /
bx .
b0 -
b0 ,
0+
1*
bx )
bx (
b10000 '
x&
0%
1$
bx #
0"
bx !
$end
#10
0*
b1 -
b1 .
b1 #
b1 (
1&
1"
0$
#20
0&
0"
#30
b10 -
b10 /
b10 #
b10 (
1&
1"
#40
0&
0"
#50
b11 -
b11 0
b11 #
b11 (
1&
1"
#60
0&
0"
#70
b100 -
b100 1
b100 #
b100 (
1&
1"
#80
0&
0"
#90
b101 -
b101 2
b101 #
b101 (
1&
1"
#100
0&
0"
#110
b110 -
b110 3
b110 #
b110 (
1&
1"
#120
0&
0"
#130
b111 -
b111 4
b111 #
b111 (
1&
1"
#140
0&
0"
#150
b1000 -
b1000 5
b1000 #
b1000 (
1&
1"
#160
0&
0"
#170
b1001 -
b1001 6
b1001 #
b1001 (
1&
1"
#180
0&
0"
#190
b1010 -
b1010 7
b1010 #
b1010 (
1&
1"
#200
0&
0"
#210
b1 ,
b1 !
b1 )
1%
1"
#220
0%
0"
#230
b10 ,
b10 !
b10 )
1%
1"
#240
0%
0"
#250
b11 ,
b11 !
b11 )
1%
1"
#260
0%
0"
#270
b100 ,
b100 !
b100 )
1%
1"
#280
0%
0"
#290
b101 ,
b101 !
b101 )
1%
1"
#300
0%
0"
