verilog/exe/SEQUENCER_DEF_new.v
`define INST_COUNTER0_S     0
`define INST_COUNTER0_E     7
`define INST_COUNTERX_S     8
`define INST_COUNTERX_E     15
`define INST_COUNTERX_WE    16
`define INST_JUMP_COUNTERX  17
`define INST_COUNTERX_CH    18
`define INST_WBUF_SEND      19
`define INST_OUTPUT_SEND    20
`define INST_CONV_CAL       21
`define INST_RADDRX_S       22 
`define INST_RADDRX_E       37
`define INST_WADDRX_S       38 
`define INST_WADDRX_E       53
`define INST_RADDRW_S       54 
`define INST_RADDRW_E       69
`define INST_RADDRX_WE      70
`define INST_WADDRX_WE      71
`define INST_RADDRW_WE      72
`define INST_WBUF_EN_CTRL_S 73
`define INST_WBUF_EN_CTRL_E 78
`define INST_OUTPUT_EN_CTRL_S 79
`define INST_OUTPUT_EN_CTRL_E 84

verilog/exe/conv_cal.v
module conv_cal(
	input wire CLK, 
	input wire RSTL,
	input wire CONV_CAL,
	input wire [7:0] COUNTER0,
	output wire [15:0] RADDRW,
	output wire RCEBW,
	output wire MAC_EN,
	output wire NL_EN,
	output wire CONV_BUSY
	);

	reg [15:0] 	pc;
	reg [2:0]   cnt;
	reg [7:0] 	counter0;
	reg [15:0] 	reg_raddrw;
	reg 		reg_macen;
	reg 		reg_nlen;


	assign RADDRW = reg_raddrw;
	assign MAC_EN = reg_macen;
	assign NL_EN = reg_nlen;
	assign CONV_BUSY = (counter0 > 1 | |cnt) ? 1:0;
	assign RCEBW   = ~|counter0;

	//counter0
  	always @(posedge CLK or negedge RSTL)  begin
		if (!RSTL) begin
			counter0 <= 0;
		end
		else if(CONV_CAL && !CONV_BUSY) begin
			counter0 <= COUNTER0;
		end
		else if(|counter0 && cnt == 3'b0) begin
			counter0 <= counter0 - 1;
		end
		else begin
			counter0 <= counter0;
		end
	end

	//cnt:アドレス用カウンタ
  	always @(posedge CLK or negedge RSTL) begin
		if (!RSTL)	
			cnt <= 0;
		else if(CONV_CAL & !CONV_BUSY)
			cnt <= 3'b101;
		else if(CONV_BUSY && ~|cnt)
			cnt <= 3'b100;
		else if(CONV_BUSY) begin
			cnt <= cnt - 1;
		end else
			cnt <= 0;
	end

	//RADDRW
	always @(posedge CLK or negedge RSTL) begin
		if (!RSTL)			
			reg_raddrw <= 1'd0;
		else if(CONV_BUSY) begin
			if(cnt == 3'b100)
				reg_raddrw <= reg_raddrw;
			else
				reg_raddrw <= reg_raddrw + 1'd1;
		end else
			reg_raddrw <= reg_raddrw;
    end

	//MAC_EN
	always@ (posedge CLK or negedge RSTL) begin
		if (!RSTL)       
			reg_macen <= 1'd0;
		else if(CONV_BUSY) begin
			if(cnt == 3'b000 | cnt == 3'b101)
				reg_macen <= 1'b1;
			else
				reg_macen <= 1'b0;
		end else
			reg_macen <= 1'b0;
	end

	//NL_EN
	always@ (posedge CLK or negedge RSTL) begin
		if (!RSTL)       
			reg_nlen <= 1'd0;
		else if(CONV_BUSY) begin
			if(cnt == 3'b001)
				reg_nlen <= 1'b0;
			else
				reg_nlen <= 1'b1;
		end else
			reg_nlen <= 1'b0;
	end


endmodule

verilog/exe/output_send.v
module output_send(
	input wire CLK, 
	input wire RSTL,
	input wire OUTPUT_SEND,
	input wire [7:0] COUNTER0,
	input wire [5:0] OUTPUT_EN_CTRL_I,
	output wire [15:0] WADDRX,
	output wire WCEBX,
	output wire OUTPUT_EN,
	output wire [5:0] OUTPUT_EN_CTRL,
	output wire OUTPUT_BUSY
	);

	reg [15:0] 	pc;
	reg [2:0]   cnt;
	reg [7:0] 	counter0;
	reg [15:0] 	reg_waddrx;
	reg			reg_wcebx;
	reg 		reg_outputen;
	reg [5:0]  	reg_outputenctrl;


	assign WADDRX = reg_waddrx;
	assign OUTPUT_EN_CTRL = reg_outputenctrl;
	assign OUTPUT_BUSY = (counter0 > 1 | |cnt) ? 1:0;
	assign WCEBX   = ~|counter0;
	assign OUTPUT_EN = |counter0;

	//counter0
  	always @(posedge CLK or negedge RSTL)  begin
		if (!RSTL) begin
			counter0 <= 0;
		end
		else if(OUTPUT_SEND && !OUTPUT_BUSY) begin
			counter0 <= COUNTER0;
		end
		else if(|counter0 && cnt == 3'b0) begin
			counter0 <= counter0 - 1;
		end
		else begin
			counter0 <= counter0;
		end
	end

	//cnt:アドレス用カウンタ
  	always @(posedge CLK or negedge RSTL) begin
		if (!RSTL)	
			cnt <= 0;
		else if(OUTPUT_SEND & !OUTPUT_BUSY)
			cnt <= 3'b100;
		else if(OUTPUT_BUSY && ~|cnt)
			cnt <= 3'b011;
		else if(OUTPUT_BUSY) begin
			cnt <= cnt - 1;
		end else
			cnt <= 0;
	end

	//WADDRX
	always @(posedge CLK or negedge RSTL) begin
		if (!RSTL)			
			reg_waddrx <= 1'd0;
		else if(OUTPUT_BUSY)
			reg_waddrx <= reg_waddrx + 1'd1;
		else
			reg_waddrx <= reg_waddrx;
    end

	//OUTPUT_EN_CTRL
	always@ (posedge CLK or negedge RSTL) begin
		if (!RSTL)       
			reg_outputenctrl <= 1'd0;
		else if(OUTPUT_SEND & !OUTPUT_BUSY)
			reg_outputenctrl <= OUTPUT_EN_CTRL_I;
		else if(OUTPUT_BUSY & ~|cnt)
			reg_outputenctrl <= reg_outputenctrl + 1'd1;
		else
			reg_outputenctrl <= reg_outputenctrl;
	end


endmodule

verilog/exe/wbuf_send.v
module wbuf_send(
	input wire CLK, 
	input wire RSTL,
	input wire WBUF_SEND,
	input wire [7:0] COUNTER0,
	input wire [5:0] WBUF_EN_CTRL_I,
	output wire [15:0] RADDRX,
	output wire RCEBX,
	output wire WBUF_EN,
	output wire [5:0] WBUF_EN_CTRL,
	output wire WBUF_BUSY
	);

	reg [15:0] 	pc;
	reg [2:0]   cnt;
	reg [7:0] 	counter0;
	reg [15:0] 	reg_raddrx;
	reg			reg_rcebx;
	reg 		reg_wbufen;
	reg [5:0]  	reg_wbufenctrl;


	assign RADDRX = reg_raddrx;
	assign WBUF_EN_CTRL = reg_wbufenctrl;
	assign WBUF_BUSY = (counter0 > 1 | |cnt) ? 1:0;
	assign RCEBX   = ~|counter0;
	assign WBUF_EN = |counter0;

	//counter0
  	always @(posedge CLK or negedge RSTL)  begin
		if (!RSTL) begin
			counter0 <= 0;
		end
		else if(WBUF_SEND && !WBUF_BUSY) begin
			counter0 <= COUNTER0;
		end
		else if(|counter0 && cnt == 3'b0) begin
			counter0 <= counter0 - 1;
		end
		else begin
			counter0 <= counter0;
		end
	end

	//cnt:アドレス用カウンタ
  	always @(posedge CLK or negedge RSTL) begin
		if (!RSTL)	
			cnt <= 0;
		else if(WBUF_SEND & !WBUF_BUSY)
			cnt <= 3'b100;
		else if(WBUF_BUSY && ~|cnt)
			cnt <= 3'b011;
		else if(WBUF_BUSY) begin
			cnt <= cnt - 1;
		end else
			cnt <= 0;
	end

	//RADDRX
	always @(posedge CLK or negedge RSTL) begin
		if (!RSTL)			
			reg_raddrx <= 1'd0;
		else if(WBUF_BUSY)
			reg_raddrx <= reg_raddrx + 1'd1;
		else
			reg_raddrx <= reg_raddrx;
    end

	//WBUF_EN_CTRL
	always@ (posedge CLK or negedge RSTL) begin
		if (!RSTL)       
			reg_wbufenctrl <= 1'd0;
		else if(WBUF_SEND & !WBUF_BUSY)
			reg_wbufenctrl <= WBUF_EN_CTRL_I;
		else if(WBUF_BUSY & ~|cnt)
			reg_wbufenctrl <= reg_wbufenctrl + 1'd1;
		else
			reg_wbufenctrl <= reg_wbufenctrl;
	end


endmodule

verilog/exe/SEQUENCER_new.v
`include "SEQUENCER_DEF_new.v"

module SEQUENCER (input wire CLK,
                  input wire RSTL,
                  input wire PURGE,
                  input wire MBUSYW,
                  input wire MBUSYXI,
                  input wire MBUSYXO,
                  input wire [255:0] QI,
                  output wire [15:0] RADDRI,
                  output wire RCEBI,
                  output wire [15:0] RADDRX,
                  output wire [15:0] RADDRW,
                  output wire [15:0] WADDRX,
                  output wire BANKX,
                  output wire BANKW,
                  output wire RCEBW,
                  output wire RCEBX,
                  output wire WCEBX,
                  output wire REQW,
                  output wire WBUF_PURGE,
                  output wire WBUF_EN,
                  output wire [5:0] WBUF_EN_CTRL,
                  output wire WBUF_ALL_EN,
                  output wire WBUF_SWITCH,
                  output wire FC_WEIGHT_EN,
                  output wire NL_EN,
                  output wire SHIFT_MODE,
                  output wire [1:0] NL_SEL,
                  output wire MAC_EN,
                  output wire RESULT_REQ,
                  output wire [3:0] OLSB,
                  output wire RESULT_PURGE,
                  output wire OUTPUT_EN,
                  output wire [5:0] OUTPUT_EN_CTRL,
                  output wire I_COMPARE_EN,
                  output wire I_COMPARE_MODE,
                  output wire I_COMPARE_SWITCH,
                  output wire O_COMPARE_EN,
                  output wire O_COMPARE_MODE,
                  output wire O_COMPARE_SWITCH,
                  output wire CAL_MODE,
                  output wire CONV_FC_MODE,
                  output wire FEEDBACK_MODE,
                  output wire CONF_EN,
                  output wire I_COMPARE_REGEN,
                  output wire [1:0] NL_LOOP_SEL,
                  output wire SEQ_LOAD_I,
                  output wire SEQ_FIN,
                  output wire SEQ_STARTW,
                  output wire SEQ_STARTX,
                  output wire SEQ_STARTX_OUT,
                  output wire RCEBX0);
    
    reg [15:0] pc; //SRAM（マイクロコード）の何行目からもってくるか
    reg [7:0] counter1; //ループ回数
    reg [7:0] counter2; //ループ回数
    reg [7:0] counter3; //ループ回数
    reg [15:0] reg_raddrx; //SRAMからの読み取りアドレス
    reg [15:0] reg_waddrx; //SRAMアドレス
    reg [15:0] reg_raddrw;
    reg [15:0] reg_raddrx_bak;
    reg [15:0] reg_raddrw_bak;
    reg [5:0]  reg_wbufenctrl;
    reg [5:0]  reg_outputenctrl;
    reg        reg_switch;
    reg [15:0] reg_raddrx_latch;
    reg [15:0] reg_waddrx_latch;
    reg [15:0] reg_raddrw_latch;
    reg [5:0]  reg_wbufenctrl_latch;
    reg [5:0]  reg_outputenctrl_latch;
    reg        reg_switch_latch;
    reg [255:0] qi_latch;
    wire [7:0] counter_end;
    reg [2:0] cnt;
    reg [7:0] counter;
    wire [15:0] counter_en;
    wire module_busy;
    wire wbuf_busy;
    wire module_en;
    reg  pc_adjust;

    assign RADDRI = {pc[14:0],1'b0};
    assign RCEBI  = 1'b0;
    assign counter_en = QI[`INST_COUNTER0_E:`INST_COUNTER0_S];
    assign module_busy = wbuf_busy | output_busy | conv_busy;
    assign module_en = QI[`INST_WBUF_SEND] | QI[`INST_OUTPUT_SEND] | QI[`INST_CONV_CAL];

    //PC
    always@ (posedge CLK or negedge RSTL)
    begin
        if (!RSTL)                          pc <= 16'b0;
        else if (PURGE)                     pc <= 16'b0;
        else if (module_busy)               pc <= pc;
        else if (!pc_adjust & module_en)    pc <= pc;
        else                                pc <= pc + 1'b1;
    end
    
    //pc_adjust
    always@ (posedge CLK or negedge RSTL)
    begin
        if (!RSTL)      pc_adjust <= 0;
        else if (PURGE) pc_adjust <= 0;
        else            pc_adjust <= module_busy;
    end

    //RADDRX
    wire [15:0] raddrx;
    assign raddrx = reg_raddrx;
    always@ (posedge CLK or negedge RSTL)
    begin
        if (!RSTL)       reg_raddrx <= 16'b0;
        else if (PURGE)  reg_raddrx <= 16'b0;
        else begin
            case(QI[`INST_RADDRX_WE])
                1'b0:
                    case(QI[`INST_RADDRX_E])
                        1'b0:
                            reg_raddrx <= reg_raddrx + QI[`INST_RADDRX_E - 1:`INST_RADDRX_S];
                        1'b1:
                            reg_raddrx <= reg_raddrx - QI[`INST_RADDRX_E - 1:`INST_RADDRX_S];
                    endcase
                1'b1:
                    reg_raddrx <= QI[`INST_RADDRX_E:`INST_RADDRX_S];
            endcase
        end
    end

    //命令モジュール呼び出し //.下位input(上位input) or .下位output(上位output)
    wbuf_send wbuf_send_0(
        //input
        .CLK(CLK),
        .RSTL(RSTL),
        .WBUF_SEND(QI[`INST_WBUF_SEND]),
        .COUNTER0(QI[`INST_COUNTER0_E:`INST_COUNTER0_S]),
        .WBUF_EN_CTRL_I(QI[`INST_WBUF_EN_CTRL_E:`INST_WBUF_EN_CTRL_S]),
        //output
        .RADDRX(RADDRX),
        .RCEBX(RCEBX),
        .WBUF_EN(WBUF_EN),
        .WBUF_EN_CTRL(WBUF_EN_CTRL),
        .WBUF_BUSY(wbuf_busy)
    );

    output_send output_send_0(
        //input
        .CLK(CLK),
        .RSTL(RSTL),
        .OUTPUT_SEND(QI[`INST_OUTPUT_SEND]),
        .COUNTER0(QI[`INST_COUNTER0_E:`INST_COUNTER0_S]),
        .OUTPUT_EN_CTRL_I(QI[`INST_OUTPUT_EN_CTRL_E:`INST_OUTPUT_EN_CTRL_S]),
        //output
        .WADDRX(WADDRX),
        .WCEBX(WCEBX),
        .OUTPUT_EN(OUTPUT_EN),
        .OUTPUT_EN_CTRL(OUTPUT_EN_CTRL),
        .OUTPUT_BUSY(output_busy)
    );

    conv_cal conv_cal_0(
        //input
        .CLK(CLK),
        .RSTL(RSTL),
        .CONV_CAL(QI[`INST_CONV_CAL]),
        .COUNTER0(QI[`INST_COUNTER0_E:`INST_COUNTER0_S]),
        //output
        .RADDRW(RADDRW),
        .RCEBW(RCEBW),
        .MAC_EN(MAC_EN),
        .NL_EN(NL_EN),
        .CONV_BUSY(conv_busy)
    );


endmodule

verilog/exe/sequencer_new_test.v
`timescale	100ps/100ps

module sequencer_test;

parameter STEP = 50;

reg clk,rstn,purge;
reg [255:0] q;
wire [15:0] a;
wire [15:0] pc;
wire ceb;
reg [255:0] memory [0:100];

always begin
    clk = 1; #(STEP/2);
    clk = 0; #(STEP/2);
end

//ssign q = (!ceb) ? memory[{2'b0,a[14:1]}] : 255'b0;
always @(posedge clk) begin
    if (!ceb) q <= memory[{2'b0,a[14:1]}];
    else q <= 255'b0;
end

SEQUENCER SEQUENCER_0(
.CLK(clk),
.RSTL(rstn),
.PURGE(purge),
.QI(q),
.RADDRI(a),
.RCEBI(ceb)
);

initial begin
    $dumpfile("sequencer_new_test.vcd");
    $dumpvars(0,SEQUENCER_0);
    $readmemb("memfile.dat", memory);

    rstn = 0;
    purge = 0;

    #(STEP * 2 + 1)
                rstn = 1;

    #STEP
                purge = 0;

    #(STEP * 20000) 
            $dumpflush;
    #STEP   $finish;

end

endmodule

verilog/exe/sequencer_new_test.vcd
$date
	Thu Jan 21 17:54:10 2021
$end
$version
	Icarus Verilog
$end
$timescale
	100ps
$end
$scope module sequencer_test $end
$scope module SEQUENCER_0 $end
$var wire 1 ! BANKW $end
$var wire 1 " BANKX $end
$var wire 1 # CAL_MODE $end
$var wire 1 $ CLK $end
$var wire 1 % CONF_EN $end
$var wire 1 & CONV_FC_MODE $end
$var wire 1 ' FC_WEIGHT_EN $end
$var wire 1 ( FEEDBACK_MODE $end
$var wire 1 ) I_COMPARE_EN $end
$var wire 1 * I_COMPARE_MODE $end
$var wire 1 + I_COMPARE_REGEN $end
$var wire 1 , I_COMPARE_SWITCH $end
$var wire 1 - MBUSYW $end
$var wire 1 . MBUSYXI $end
$var wire 1 / MBUSYXO $end
$var wire 2 0 NL_LOOP_SEL [1:0] $end
$var wire 2 1 NL_SEL [1:0] $end
$var wire 4 2 OLSB [3:0] $end
$var wire 1 3 O_COMPARE_EN $end
$var wire 1 4 O_COMPARE_MODE $end
$var wire 1 5 O_COMPARE_SWITCH $end
$var wire 1 6 PURGE $end
$var wire 256 7 QI [255:0] $end
$var wire 1 8 RCEBI $end
$var wire 1 9 RCEBX0 $end
$var wire 1 : REQW $end
$var wire 1 ; RESULT_PURGE $end
$var wire 1 < RESULT_REQ $end
$var wire 1 = RSTL $end
$var wire 1 > SEQ_FIN $end
$var wire 1 ? SEQ_LOAD_I $end
$var wire 1 @ SEQ_STARTW $end
$var wire 1 A SEQ_STARTX $end
$var wire 1 B SEQ_STARTX_OUT $end
$var wire 1 C SHIFT_MODE $end
$var wire 1 D WBUF_ALL_EN $end
$var wire 1 E WBUF_PURGE $end
$var wire 1 F WBUF_SWITCH $end
$var wire 1 G module_busy $end
$var wire 1 H module_en $end
$var wire 16 I raddrx [15:0] $end
$var wire 1 J wbuf_busy $end
$var wire 1 K output_busy $end
$var wire 16 L counter_en [15:0] $end
$var wire 1 M conv_busy $end
$var wire 1 N WCEBX $end
$var wire 6 O WBUF_EN_CTRL [5:0] $end
$var wire 1 P WBUF_EN $end
$var wire 16 Q WADDRX [15:0] $end
$var wire 1 R RCEBX $end
$var wire 1 S RCEBW $end
$var wire 16 T RADDRX [15:0] $end
$var wire 16 U RADDRW [15:0] $end
$var wire 16 V RADDRI [15:0] $end
$var wire 6 W OUTPUT_EN_CTRL [5:0] $end
$var wire 1 X OUTPUT_EN $end
$var wire 1 Y NL_EN $end
$var wire 1 Z MAC_EN $end
$var reg 16 [ pc [15:0] $end
$var reg 1 \ pc_adjust $end
$var reg 16 ] reg_raddrx [15:0] $end
$scope module conv_cal_0 $end
$var wire 1 $ CLK $end
$var wire 1 ^ CONV_CAL $end
$var wire 8 _ COUNTER0 [7:0] $end
$var wire 1 Z MAC_EN $end
$var wire 1 Y NL_EN $end
$var wire 16 ` RADDRW [15:0] $end
$var wire 1 = RSTL $end
$var wire 1 S RCEBW $end
$var wire 1 M CONV_BUSY $end
$var reg 3 a cnt [2:0] $end
$var reg 8 b counter0 [7:0] $end
$var reg 1 c reg_macen $end
$var reg 1 d reg_nlen $end
$var reg 16 e reg_raddrw [15:0] $end
$upscope $end
$scope module output_send_0 $end
$var wire 1 $ CLK $end
$var wire 8 f COUNTER0 [7:0] $end
$var wire 6 g OUTPUT_EN_CTRL [5:0] $end
$var wire 6 h OUTPUT_EN_CTRL_I [5:0] $end
$var wire 1 i OUTPUT_SEND $end
$var wire 1 = RSTL $end
$var wire 16 j WADDRX [15:0] $end
$var wire 1 N WCEBX $end
$var wire 1 X OUTPUT_EN $end
$var wire 1 K OUTPUT_BUSY $end
$var reg 3 k cnt [2:0] $end
$var reg 8 l counter0 [7:0] $end
$var reg 6 m reg_outputenctrl [5:0] $end
$var reg 16 n reg_waddrx [15:0] $end
$upscope $end
$scope module wbuf_send_0 $end
$var wire 1 $ CLK $end
$var wire 8 o COUNTER0 [7:0] $end
$var wire 16 p RADDRX [15:0] $end
$var wire 1 = RSTL $end
$var wire 6 q WBUF_EN_CTRL [5:0] $end
$var wire 6 r WBUF_EN_CTRL_I [5:0] $end
$var wire 1 s WBUF_SEND $end
$var wire 1 P WBUF_EN $end
$var wire 1 J WBUF_BUSY $end
$var wire 1 R RCEBX $end
$var reg 3 t cnt [2:0] $end
$var reg 8 u counter0 [7:0] $end
$var reg 16 v reg_raddrx [15:0] $end
$var reg 6 w reg_wbufenctrl [5:0] $end
$upscope $end
$upscope $end
$upscope $end
$enddefinitions $end
#0
$dumpvars
b0 w
b0 v
b0 u
b0 t
xs
bx r
b0 q
b0 p
bx o
b0 n
b0 m
b0 l
b0 k
b0 j
xi
bx h
b0 g
bx f
b0 e
0d
0c
b0 b
b0 a
b0 `
bx _
x^
b0 ]
0\
b0 [
0Z
0Y
0X
b0 W
b0 V
b0 U
b0 T
1S
1R
b0 Q
0P
b0 O
1N
0M
b0xxxxxxxx L
0K
0J
b0 I
xH
0G
zF
zE
zD
zC
zB
zA
z@
z?
z>
0=
z<
z;
z:
z9
08
bx 7
06
z5
z4
z3
bz 2
bz 1
bz 0
z/
z.
z-
z,
z+
z*
z)
z(
z'
z&
z%
1$
z#
z"
z!
$end
#25
0$
#50
0H
b0 L
0s
b0 o
b0 r
0i
b0 f
b0 h
0^
b0 _
b1110000000000000000000000000000000000000000000000000000000000000000000000 7
1$
#75
0$
#100
1$
#101
1=
#125
0$
#150
b10 V
b1 [
1$
#175
0$
#200
1H
b100 V
b100 L
1s
b100 o
b100 f
b100 _
b10 [
b1100000000000000000000000000000000000000000000000000010000000000000000100 7
1$
#225
0$
#250
1G
1J
0H
b0 L
0s
b0 o
b0 f
b0 _
b100 t
0R
1P
b100 u
b1100000000000000000000000000000000000000000000000000000000000000000000000 7
1$
#275
0$
#300
b11 t
b1 T
b1 p
b1 v
1\
1$
#325
0$
#350
b10 T
b10 p
b10 v
b10 t
1$
#375
0$
#400
b1 t
b11 T
b11 p
b11 v
1$
#425
0$
#450
b100 T
b100 p
b100 v
b0 t
1$
#475
0$
#500
b11 u
b11 t
b101 T
b101 p
b101 v
b1 O
b1 q
b1 w
1$
#525
0$
#550
b110 T
b110 p
b110 v
b10 t
1$
#575
0$
#600
b1 t
b111 T
b111 p
b111 v
1$
#625
0$
#650
b1000 T
b1000 p
b1000 v
b0 t
1$
#675
0$
#700
b10 u
b11 t
b1001 T
b1001 p
b1001 v
b10 O
b10 q
b10 w
1$
#725
0$
#750
b1010 T
b1010 p
b1010 v
b10 t
1$
#775
0$
#800
b1 t
b1011 T
b1011 p
b1011 v
1$
#825
0$
#850
b1100 T
b1100 p
b1100 v
b0 t
1$
#875
0$
#900
b1 u
b11 t
b1101 T
b1101 p
b1101 v
b11 O
b11 q
b11 w
1$
#925
0$
#950
b1110 T
b1110 p
b1110 v
b10 t
1$
#975
0$
#1000
b1 t
b1111 T
b1111 p
b1111 v
1$
#1025
0$
#1050
0G
0J
b10000 T
b10000 p
b10000 v
b0 t
1$
#1075
0$
#1100
b110 V
1R
0P
b0 u
b11 [
0\
1$
#1125
0$
#1150
1H
b1000 V
b100 L
b100 o
1i
b100 f
b100 _
b100 [
b1000000000000000000000000000000000000000000000000000100000000000000000100 7
1$
#1175
0$
#1200
1G
1K
0H
b0 L
b0 o
0i
b0 f
b0 _
0N
1X
b100 l
b100 k
b1000000000000000000000000000000000000000000000000000000000000000000000000 7
1$
#1225
0$
#1250
1\
b1 Q
b1 j
b1 n
b11 k
1$
#1275
0$
#1300
b10 k
b10 Q
b10 j
b10 n
1$
#1325
0$
#1350
b11 Q
b11 j
b11 n
b1 k
1$
#1375
0$
#1400
b0 k
b100 Q
b100 j
b100 n
1$
#1425
0$
#1450
b1 W
b1 g
b1 m
b101 Q
b101 j
b101 n
b11 k
b11 l
1$
#1475
0$
#1500
b10 k
b110 Q
b110 j
b110 n
1$
#1525
0$
#1550
b111 Q
b111 j
b111 n
b1 k
1$
#1575
0$
#1600
b0 k
b1000 Q
b1000 j
b1000 n
1$
#1625
0$
#1650
b10 W
b10 g
b10 m
b1001 Q
b1001 j
b1001 n
b11 k
b10 l
1$
#1675
0$
#1700
b10 k
b1010 Q
b1010 j
b1010 n
1$
#1725
0$
#1750
b1011 Q
b1011 j
b1011 n
b1 k
1$
#1775
0$
#1800
b0 k
b1100 Q
b1100 j
b1100 n
1$
#1825
0$
#1850
b11 W
b11 g
b11 m
b1101 Q
b1101 j
b1101 n
b11 k
b1 l
1$
#1875
0$
#1900
b10 k
b1110 Q
b1110 j
b1110 n
1$
#1925
0$
#1950
b1111 Q
b1111 j
b1111 n
b1 k
1$
#1975
0$
#2000
0G
0K
b0 k
b10000 Q
b10000 j
b10000 n
1$
#2025
0$
#2050
b1010 V
0\
b101 [
1N
0X
b0 l
1$
#2075
0$
#2100
1H
b1100 V
b100 L
b100 o
b100 f
1^
b100 _
b110 [
b1000000000000000000100 7
1$
#2125
0$
#2150
1G
1M
0H
b0 L
b0 o
b0 f
0^
b0 _
b101 a
0S
b100 b
b0 7
1$
#2175
0$
#2200
b100 a
b1 U
b1 `
b1 e
1Z
1c
1Y
1d
1\
1$
#2225
0$
#2250
0Z
0c
b11 a
1$
#2275
0$
#2300
b10 a
b10 U
b10 `
b10 e
1$
#2325
0$
#2350
b11 U
b11 `
b11 e
b1 a
1$
#2375
0$
#2400
b0 a
b100 U
b100 `
b100 e
0Y
0d
1$
#2425
0$
#2450
1Y
1d
1Z
1c
b101 U
b101 `
b101 e
b100 a
b11 b
1$
#2475
0$
#2500
b11 a
0Z
0c
1$
#2525
0$
#2550
b110 U
b110 `
b110 e
b10 a
1$
#2575
0$
#2600
b1 a
b111 U
b111 `
b111 e
1$
#2625
0$
#2650
0Y
0d
b1000 U
b1000 `
b1000 e
b0 a
1$
#2675
0$
#2700
b10 b
b100 a
b1001 U
b1001 `
b1001 e
1Z
1c
1Y
1d
1$
#2725
0$
#2750
0Z
0c
b11 a
1$
#2775
0$
#2800
b10 a
b1010 U
b1010 `
b1010 e
1$
#2825
0$
#2850
b1011 U
b1011 `
b1011 e
b1 a
1$
#2875
0$
#2900
b0 a
b1100 U
b1100 `
b1100 e
0Y
0d
1$
#2925
0$
#2950
1Y
1d
1Z
1c
b1101 U
b1101 `
b1101 e
b100 a
b1 b
1$
#2975
0$
#3000
b11 a
0Z
0c
1$
#3025
0$
#3050
b1110 U
b1110 `
b1110 e
b10 a
1$
#3075
0$
#3100
b1 a
b1111 U
b1111 `
b1111 e
1$
#3125
0$
#3150
0G
0M
0Y
0d
b10000 U
b10000 `
b10000 e
b0 a
1$
#3175
0$
#3200
b1110 V
1S
b0 b
b111 [
0\
1$
#3225
0$
#3250
b10000 V
b1000 [
1$
#3275
0$
#3300
b10010 V
b1001 [
1$
#3325
0$
#3350
xH
b10100 V
b0xxxxxxxx L
xs
bx o
bx r
xi
bx f
bx h
x^
bx _
b1010 [
bx 7
1$
#3375
0$
#3400
b10110 V
b1011 [
1$
#3425
0$
#3450
b11000 V
b1100 [
1$
#3475
0$
#3500
b11010 V
b1101 [
1$
#3525
0$
#3550
b11100 V
b1110 [
1$
#3575
0$
#3600
b11110 V
b1111 [
1$
#3625
0$
#3650
b100000 V
b10000 [
1$
#3675
0$
#3700
b100010 V
b10001 [
1$
#3725
0$
#3750
b100100 V
b10010 [
1$
#3775
0$
#3800
b100110 V
b10011 [
1$
#3825
0$
#3850
b101000 V
b10100 [
1$
#3875
0$
#3900
b101010 V
b10101 [
1$
#3925
0$
#3950
b101100 V
b10110 [
1$
#3975
0$
#4000
b101110 V
b10111 [
1$
#4025
0$
#4050
b110000 V
b11000 [
1$
#4075
0$
#4100
b110010 V
b11001 [
1$
#4125
0$
#4150
b110100 V
b11010 [
1$
#4175
0$
#4200
b110110 V
b11011 [
1$
#4225
0$
#4250
b111000 V
b11100 [
1$
#4275
0$
#4300
b111010 V
b11101 [
1$
#4325
0$
#4350
b111100 V
b11110 [
1$
#4375
0$
#4400
b111110 V
b11111 [
1$
#4425
0$
#4450
b1000000 V
b100000 [
1$
#4475
0$
#4500
b1000010 V
b100001 [
1$
#4525
0$
#4550
b1000100 V
b100010 [
1$
#4575
0$
#4600
b1000110 V
b100011 [
1$
#4625
0$
#4650
b1001000 V
b100100 [
1$
#4675
0$
#4700
b1001010 V
b100101 [
1$
#4725
0$
#4750
b1001100 V
b100110 [
1$
#4775
0$
#4800
b1001110 V
b100111 [
1$
#4825
0$
#4850
b1010000 V
b101000 [
1$
#4875
0$
#4900
b1010010 V
b101001 [
1$
#4925
0$
#4950
b1010100 V
b101010 [
1$
#4975
0$
#5000
b1010110 V
b101011 [
1$
#5025
0$
#5050
b1011000 V
b101100 [
1$
#5075
0$
#5100
b1011010 V
b101101 [
1$
#5125
0$
#5150
b1011100 V
b101110 [
1$
#5175
0$
#5200
b1011110 V
b101111 [
1$
#5225
0$
#5250
b1100000 V
b110000 [
1$
#5275
0$
#5300
b1100010 V
b110001 [
1$
#5325
0$
#5350
b1100100 V
b110010 [
1$
#5375
0$
#5400
b1100110 V
b110011 [
1$
#5425
0$
#5450
b1101000 V
b110100 [
1$
#5475
0$
#5500
b1101010 V
b110101 [
1$
#5525
0$
#5550
b1101100 V
b110110 [
1$
#5575
0$
#5600
b1101110 V
b110111 [
1$
#5625
0$
#5650
b1110000 V
b111000 [
1$
#5675
0$
#5700
b1110010 V
b111001 [
1$
#5725
0$
#5750
b1110100 V
b111010 [
1$
#5775
0$
#5800
b1110110 V
b111011 [
1$
#5825
0$
#5850
b1111000 V
b111100 [
1$
#5875
0$
#5900
b1111010 V
b111101 [
1$
#5925
0$
#5950
b1111100 V
b111110 [
1$
#5975
0$
#6000
b1111110 V
b111111 [
1$
#6025
0$
#6050
b10000000 V
b1000000 [
1$
#6075
0$
#6100
b10000010 V
b1000001 [
1$
#6125
0$
#6150
b10000100 V
b1000010 [
1$
#6175
0$
#6200
b10000110 V
b1000011 [
1$
#6225
0$
#6250
b10001000 V
b1000100 [
1$
#6275
0$
#6300
b10001010 V
b1000101 [
1$
#6325
0$
#6350
b10001100 V
b1000110 [
1$
#6375
0$
#6400
b10001110 V
b1000111 [
1$
#6425
0$
#6450
b10010000 V
b1001000 [
1$
#6475
0$
#6500
b10010010 V
b1001001 [
1$
#6525
0$
#6550
b10010100 V
b1001010 [
1$
#6575
0$
#6600
b10010110 V
b1001011 [
1$
#6625
0$
#6650
b10011000 V
b1001100 [
1$
#6675
0$
#6700
b10011010 V
b1001101 [
1$
#6725
0$
#6750
b10011100 V
b1001110 [
1$
#6775
0$
#6800
b10011110 V
b1001111 [
1$
#6825
0$
#6850
b10100000 V
b1010000 [
1$
#6875
0$
#6900
b10100010 V
b1010001 [
1$
#6925
0$
#6950
b10100100 V
b1010010 [
1$
#6975
0$
#7000
b10100110 V
b1010011 [
1$
#7025
0$
#7050
b10101000 V
b1010100 [
1$
#7075
0$
#7100
b10101010 V
b1010101 [
1$
#7125
0$
#7150
b10101100 V
b1010110 [
1$
#7175
0$
#7200
b10101110 V
b1010111 [
1$
#7225
0$
#7250
b10110000 V
b1011000 [
1$
#7275
0$
#7300
b10110010 V
b1011001 [
1$
#7325
0$
#7350
b10110100 V
b1011010 [
1$
#7375
0$
#7400
b10110110 V
b1011011 [
1$
#7425
0$
#7450
b10111000 V
b1011100 [
1$
#7475
0$
#7500
b10111010 V
b1011101 [
1$
#7525
0$
#7550
b10111100 V
b1011110 [
1$
#7575
0$
#7600
b10111110 V
b1011111 [
1$
#7625
0$
#7650
b11000000 V
b1100000 [
1$
#7675
0$
#7700
b11000010 V
b1100001 [
1$
