verilog/exe/SEQUENCER_DEF_new.v
`define INST_WBUF_SEND 0
`define INST_COUNTER0_S 1
`define INST_COUNTER0_E 8
`define INST_RADDRX_S 9
`define INST_RADDRX_E 24
`define INST_WBUF_EN_CTRL_S 25
`define INST_WBUF_EN_CTRL_E 30

verilog/exe/wbuf_send.v
module wbuf_send(
	input wire CLK, 
	input wire RSTL,
	input wire WBUF_SEND,
	input wire [7:0] COUNTER0,
	input wire [15:0] raddrx,
	input wire [5:0] wbuf_en_ctrl,
	output wire [15:0] RADDRX,
	output wire RCEBX,
	output wire WBUF_EN,
	output wire [5:0] WBUF_EN_CTRL,
	output wire [7:0] COUNTER_END
	);

	reg [15:0] 	pc;
	reg [2:0]	cnt;
	reg [7:0] 	counter0;
	reg [15:0] 	reg_raddrx;
	reg			reg_rcebx;
	reg 		reg_wbufen;
	reg [5:0]  	reg_wbufenctrl;

	assign RADDRX = reg_raddrx;
	assign RCEBX = reg_rcebx;
	assign WBUF_EN = reg_wbufen;
	assign WBUF_EN_CTRL = reg_wbufenctrl;
	assign COUNTER_END = counter0;

	//counter0
  	always @(posedge CLK or negedge RSTL)  begin
		if (!RSTL)
			counter0 <= 1'd0;
		else if(WBUF_SEND) begin
			if(counter0 == 1'd0)
				counter0 <= COUNTER0;
			else if(cnt == 3'b100)
				counter0 <= counter0 - 1;
			else
				counter0 <= counter0;
		end else
			counter0 <= 1'd0;
	end

	//cnt:アドレス用カウンタ(4サイクル)
  	always @(posedge CLK or negedge RSTL) begin
		if (!RSTL)			
			cnt <= 3'b000;
		else if(WBUF_SEND) begin
			if(cnt == 3'b100) begin
				if(counter0 == 16'd1)
					cnt <= 3'b000;
				else
					cnt <= 3'b001;
			end else
        		cnt <= cnt + 1;
		end else
			cnt <= 3'b000;
	end

	//RCEBX
  	always @(posedge CLK or negedge RSTL) begin
		if (!RSTL)			
			reg_rcebx <= 1;
		else if(WBUF_SEND)
      		reg_rcebx <= 0;
		else
			reg_rcebx <= 1;
	end

	//WBUF_EN
  	always @(posedge CLK or negedge RSTL) begin
		if (!RSTL)			
			reg_wbufen <= 3'b000;
		else if(WBUF_SEND)
      		reg_wbufen <= 1;
		else
			reg_wbufen <= 0;
	end

	//RADDRX
	always @(posedge CLK or negedge RSTL) begin
		if (!RSTL)			
			reg_raddrx <= 1'd0;
		else if(WBUF_SEND) begin
			if(counter0 == COUNTER0 && cnt == 3'b001)
				reg_raddrx <= raddrx;
			else
				reg_raddrx <= reg_raddrx + 1'd1;
		end else
			reg_raddrx <= 1'd0;
    end

	//WBUF_EN_CTRL
	always@ (posedge CLK or negedge RSTL) begin
		if (!RSTL)       
			reg_wbufenctrl <= 1'd0;
		else if(WBUF_SEND) begin
			if(counter0 == COUNTER0 && cnt == 3'b001)
				reg_wbufenctrl <= wbuf_en_ctrl;
			else if(counter0 != 1 && cnt == 3'b100)
				reg_wbufenctrl <= reg_wbufenctrl + 1'd1;
			else
				reg_wbufenctrl <= reg_wbufenctrl;
		end else
			reg_wbufenctrl <= 1'd0;
	end


endmodule

verilog/exe/SEQUENCER_new.v
`include "SEQUENCER_DEF_new.v"

module SEQUENCER (input wire CLK,
                  input wire RSTL,
                  input wire PURGE,
                  input wire MBUSYW,
                  input wire MBUSYXI,
                  input wire MBUSYXO,
                  input wire [255:0] QI,
                  output wire [15:0] RADDRI,
                  output wire RCEBI,
                  output wire [15:0] RADDRX,
                  output wire [15:0] RADDRW,
                  output wire [15:0] WADDRX,
                  output wire BANKX,
                  output wire BANKW,
                  output wire RCEBW,
                  output wire RCEBX,
                  output wire WCEBX,
                  output wire REQW,
                  output wire WBUF_PURGE,
                  output wire WBUF_EN,
                  output wire [5:0] WBUF_EN_CTRL,
                  output wire WBUF_ALL_EN,
                  output wire WBUF_SWITCH,
                  output wire FC_WEIGHT_EN,
                  output wire NL_EN,
                  output wire SHIFT_MODE,
                  output wire [1:0] NL_SEL,
                  output wire MAC_EN,
                  output wire RESULT_REQ,
                  output wire [3:0] OLSB,
                  output wire RESULT_PURGE,
                  output wire OUTPUT_EN,
                  output wire [5:0] OUTPUT_EN_CTRL,
                  output wire I_COMPARE_EN,
                  output wire I_COMPARE_MODE,
                  output wire I_COMPARE_SWITCH,
                  output wire O_COMPARE_EN,
                  output wire O_COMPARE_MODE,
                  output wire O_COMPARE_SWITCH,
                  output wire CAL_MODE,
                  output wire CONV_FC_MODE,
                  output wire FEEDBACK_MODE,
                  output wire CONF_EN,
                  output wire I_COMPARE_REGEN,
                  output wire [1:0] NL_LOOP_SEL,
                  output wire SEQ_LOAD_I,
                  output wire SEQ_FIN,
                  output wire SEQ_STARTW,
                  output wire SEQ_STARTX,
                  output wire SEQ_STARTX_OUT,
                  output wire RCEBX0);
    
    reg [15:0] pc; //SRAM（マイクロコード）の何行目からもってくるか
    reg [7:0] counter1; //ループ回数
    reg [7:0] counter2; //ループ回数
    reg [7:0] counter3; //ループ回数
    reg [15:0] reg_raddrx; //SRAMからの読み取りアドレス
    reg [15:0] reg_waddrx; //SRAMアドレス
    reg [15:0] reg_raddrw;
    reg [15:0] reg_raddrx_bak;
    reg [15:0] reg_raddrw_bak;
    reg [5:0]  reg_wbufenctrl;
    reg [5:0]  reg_outputenctrl;
    reg        reg_switch;
    reg [15:0] reg_raddrx_latch;
    reg [15:0] reg_waddrx_latch;
    reg [15:0] reg_raddrw_latch;
    reg [5:0]  reg_wbufenctrl_latch;
    reg [5:0]  reg_outputenctrl_latch;
    reg        reg_switch_latch;
    reg [255:0] qi_latch;
    wire [7:0] counter_end;
    reg [2:0] cnt;
    reg [7:0] counter;
    
    assign RADDRI = {pc[14:0],1'b0}; //SRAMの何行目かを指定
    assign RCEBI  = 1'b0;
    assign WBUF_SWITCH    = reg_switch_latch;
    
    //PC
    always@ (posedge CLK or negedge RSTL)
    begin
        if (!RSTL)       pc <= 16'b0;
        else if (PURGE)  pc <= 16'b0;
        else begin
            case(QI[`INST_WBUF_SEND])
                1'b1:
                    if(counter != QI[`INST_COUNTER0_E:`INST_COUNTER0_S])
                        pc <= pc;
                    else
                        pc <= pc + 1;
                default:
                    pc <= pc + 1;
            endcase
        end
    end

    //counter
  	always @(posedge CLK or negedge RSTL)  begin
		if (!RSTL)
			counter <= 1'd0;
		else if(QI[`INST_WBUF_SEND]) begin
			if(cnt == 3'b100)
				counter <= counter + 1;
			else
				counter <= counter;
		end else
			counter <= 1'd0;
	end

    //cnt:モジュール用カウンタ(wbuf & output)
    always@ (posedge CLK or negedge RSTL)
    begin
        if(!RSTL)       cnt <= 0;
        else if(PURGE)  cnt <= 0; 
        else if(QI[`INST_WBUF_SEND]) begin
			if(cnt == 3'b100) begin
				if(counter == QI[`INST_COUNTER0_E:`INST_COUNTER0_S] - 1)
					cnt <= 3'b000;
				else
					cnt <= 3'b001;
			end else
        		cnt <= cnt + 1;
		end else
			cnt <= 3'b000;
    end

    //命令モジュール呼び出し //.下位input(上位input) or .下位output(上位output)
    wbuf_send wbuf_send_0(
        //input
        .CLK(CLK),
        .RSTL(RSTL),
        .WBUF_SEND(QI[`INST_WBUF_SEND]),
        .COUNTER0(QI[`INST_COUNTER0_E:`INST_COUNTER0_S]),
        .raddrx(QI[`INST_RADDRX_E:`INST_RADDRX_S]),
        .wbuf_en_ctrl(QI[`INST_WBUF_EN_CTRL_E:`INST_WBUF_EN_CTRL_S]),
        //output
        .RADDRX(RADDRX),
        .RCEBX(RCEBX),
        .WBUF_EN(WBUF_EN),
        .WBUF_EN_CTRL(WBUF_EN_CTRL),
        .COUNTER_END(counter_end)
    );

endmodule

verilog/exe/sequencer_new_test.v
`timescale	100ps/100ps

module sequencer_test;

parameter STEP = 50;

reg clk,rstn,purge;
reg [255:0] q;
wire [15:0] a;
wire [15:0] pc;
wire ceb;
reg [255:0] memory [0:100];

always begin
    clk = 1; #(STEP/2);
    clk = 0; #(STEP/2);
end

//ssign q = (!ceb) ? memory[{2'b0,a[14:1]}] : 255'b0;
always @(posedge clk) begin
    if (!ceb) q <= memory[{2'b0,a[14:1]}];
    else q <= 255'b0;
end

SEQUENCER SEQUENCER_0(
.CLK(clk),
.RSTL(rstn),
.PURGE(purge),
.QI(q),
.RADDRI(a),
.RCEBI(ceb)
);

initial begin
    $dumpfile("sequencer_new_test.vcd");
    $dumpvars(0,SEQUENCER_0);
    $readmemb("memfile.dat", memory);

    rstn = 0;
    purge = 0;

    #(STEP * 2 + 1)
                rstn = 1;

    #STEP
                purge = 0;

    #(STEP * 20000) 
            $dumpflush;
    #STEP   $finish;

end

endmodule

verilog/exe/sequencer_new_test.vcd
$date
	Thu Jan 14 19:03:48 2021
$end
$version
	Icarus Verilog
$end
$timescale
	100ps
$end
$scope module sequencer_test $end
$scope module SEQUENCER_0 $end
$var wire 1 ! BANKW $end
$var wire 1 " BANKX $end
$var wire 1 # CAL_MODE $end
$var wire 1 $ CLK $end
$var wire 1 % CONF_EN $end
$var wire 1 & CONV_FC_MODE $end
$var wire 1 ' FC_WEIGHT_EN $end
$var wire 1 ( FEEDBACK_MODE $end
$var wire 1 ) I_COMPARE_EN $end
$var wire 1 * I_COMPARE_MODE $end
$var wire 1 + I_COMPARE_REGEN $end
$var wire 1 , I_COMPARE_SWITCH $end
$var wire 1 - MAC_EN $end
$var wire 1 . MBUSYW $end
$var wire 1 / MBUSYXI $end
$var wire 1 0 MBUSYXO $end
$var wire 1 1 NL_EN $end
$var wire 2 2 NL_LOOP_SEL [1:0] $end
$var wire 2 3 NL_SEL [1:0] $end
$var wire 4 4 OLSB [3:0] $end
$var wire 1 5 OUTPUT_EN $end
$var wire 6 6 OUTPUT_EN_CTRL [5:0] $end
$var wire 1 7 O_COMPARE_EN $end
$var wire 1 8 O_COMPARE_MODE $end
$var wire 1 9 O_COMPARE_SWITCH $end
$var wire 1 : PURGE $end
$var wire 256 ; QI [255:0] $end
$var wire 16 < RADDRW [15:0] $end
$var wire 1 = RCEBI $end
$var wire 1 > RCEBW $end
$var wire 1 ? RCEBX0 $end
$var wire 1 @ REQW $end
$var wire 1 A RESULT_PURGE $end
$var wire 1 B RESULT_REQ $end
$var wire 1 C RSTL $end
$var wire 1 D SEQ_FIN $end
$var wire 1 E SEQ_LOAD_I $end
$var wire 1 F SEQ_STARTW $end
$var wire 1 G SEQ_STARTX $end
$var wire 1 H SEQ_STARTX_OUT $end
$var wire 1 I SHIFT_MODE $end
$var wire 16 J WADDRX [15:0] $end
$var wire 1 K WBUF_ALL_EN $end
$var wire 1 L WBUF_PURGE $end
$var wire 1 M WBUF_SWITCH $end
$var wire 1 N WCEBX $end
$var wire 8 O counter_end [7:0] $end
$var wire 6 P WBUF_EN_CTRL [5:0] $end
$var wire 1 Q WBUF_EN $end
$var wire 1 R RCEBX $end
$var wire 16 S RADDRX [15:0] $end
$var wire 16 T RADDRI [15:0] $end
$var reg 3 U cnt [2:0] $end
$var reg 8 V counter [7:0] $end
$var reg 16 W pc [15:0] $end
$var reg 1 X reg_switch_latch $end
$scope module wbuf_send_0 $end
$var wire 1 $ CLK $end
$var wire 8 Y COUNTER0 [7:0] $end
$var wire 8 Z COUNTER_END [7:0] $end
$var wire 16 [ RADDRX [15:0] $end
$var wire 1 R RCEBX $end
$var wire 1 C RSTL $end
$var wire 1 Q WBUF_EN $end
$var wire 6 \ WBUF_EN_CTRL [5:0] $end
$var wire 1 ] WBUF_SEND $end
$var wire 16 ^ raddrx [15:0] $end
$var wire 6 _ wbuf_en_ctrl [5:0] $end
$var reg 3 ` cnt [2:0] $end
$var reg 8 a counter0 [7:0] $end
$var reg 16 b reg_raddrx [15:0] $end
$var reg 1 c reg_rcebx $end
$var reg 1 d reg_wbufen $end
$var reg 6 e reg_wbufenctrl [5:0] $end
$upscope $end
$upscope $end
$upscope $end
$enddefinitions $end
#0
$dumpvars
b0 e
0d
1c
b0 b
b0 a
b0 `
bx _
bx ^
x]
b0 \
b0 [
b0 Z
bx Y
xX
b0 W
b0 V
b0 U
b0 T
b0 S
1R
0Q
b0 P
b0 O
zN
xM
zL
zK
bz J
zI
zH
zG
zF
zE
zD
0C
zB
zA
z@
z?
z>
0=
bz <
bx ;
0:
z9
z8
z7
bz 6
z5
bz 4
bz 3
bz 2
z1
z0
z/
z.
z-
z,
z+
z*
z)
z(
z'
z&
z%
1$
z#
z"
z!
$end
#25
0$
#50
0]
b0 Y
b0 ^
b0 _
b0 ;
1$
#75
0$
#100
1$
#101
1C
#125
0$
#150
b10 T
b1 W
1$
#175
0$
#200
b100 T
1]
b100000 Y
b10 W
b1000001 ;
1$
#225
0$
#250
0]
b0 Y
b1 U
b1 S
b1 [
b1 b
1Q
1d
0R
0c
b1 `
b100000 O
b100000 Z
b100000 a
b0 ;
1$
#275
0$
#300
b110 T
b0 O
b0 Z
b0 a
b0 `
1R
1c
0Q
0d
b0 S
b0 [
b0 b
b11 W
b0 U
1$
#325
0$
#350
b1000 T
x]
bx Y
bx ^
bx _
b100 W
bx ;
1$
#375
0$
#400
b1010 T
b101 W
1$
#425
0$
#450
b1100 T
b110 W
1$
#475
0$
#500
b1110 T
b111 W
1$
#525
0$
#550
b10000 T
b1000 W
1$
#575
0$
#600
b10010 T
b1001 W
1$
#625
0$
#650
b10100 T
b1010 W
1$
#675
0$
#700
b10110 T
b1011 W
1$
#725
0$
#750
b11000 T
b1100 W
1$
#775
0$
#800
b11010 T
b1101 W
1$
#825
0$
#850
b11100 T
b1110 W
1$
#875
0$
#900
b11110 T
b1111 W
1$
#925
0$
#950
b100000 T
b10000 W
1$
#975
0$
#1000
b100010 T
b10001 W
1$
#1025
0$
#1050
b100100 T
b10010 W
1$
#1075
0$
#1100
b100110 T
b10011 W
1$
#1125
0$
#1150
b101000 T
b10100 W
1$
#1175
0$
#1200
b101010 T
b10101 W
1$
#1225
0$
#1250
b101100 T
b10110 W
1$
#1275
0$
#1300
b101110 T
b10111 W
1$
#1325
0$
#1350
b110000 T
b11000 W
1$
#1375
0$
#1400
b110010 T
b11001 W
1$
#1425
0$
#1450
b110100 T
b11010 W
1$
#1475
0$
#1500
b110110 T
b11011 W
1$
#1525
0$
#1550
b111000 T
b11100 W
1$
#1575
0$
#1600
b111010 T
b11101 W
1$
#1625
0$
#1650
b111100 T
b11110 W
1$
#1675
0$
#1700
b111110 T
b11111 W
1$
#1725
0$
#1750
b1000000 T
b100000 W
1$
#1775
0$
#1800
b1000010 T
b100001 W
1$
#1825
0$
#1850
b1000100 T
b100010 W
1$
#1875
0$
#1900
b1000110 T
b100011 W
1$
#1925
0$
#1950
b1001000 T
b100100 W
1$
#1975
0$
#2000
b1001010 T
b100101 W
1$
#2025
0$
#2050
b1001100 T
b100110 W
1$
#2075
0$
#2100
b1001110 T
b100111 W
1$
#2125
0$
#2150
b1010000 T
b101000 W
1$
#2175
0$
#2200
b1010010 T
b101001 W
1$
#2225
0$
#2250
b1010100 T
b101010 W
1$
#2275
0$
#2300
b1010110 T
b101011 W
1$
#2325
0$
#2350
b1011000 T
b101100 W
1$
#2375
0$
#2400
b1011010 T
b101101 W
1$
#2425
0$
#2450
b1011100 T
b101110 W
1$
#2475
0$
#2500
b1011110 T
b101111 W
1$
#2525
0$
#2550
b1100000 T
b110000 W
1$
#2575
0$
#2600
b1100010 T
b110001 W
1$
#2625
0$
#2650
b1100100 T
b110010 W
1$
#2675
0$
#2700
b1100110 T
b110011 W
1$
#2725
0$
#2750
b1101000 T
b110100 W
1$
#2775
0$
#2800
b1101010 T
b110101 W
1$
#2825
0$
#2850
b1101100 T
b110110 W
1$
#2875
0$
#2900
b1101110 T
b110111 W
1$
#2925
0$
#2950
b1110000 T
b111000 W
1$
#2975
0$
#3000
b1110010 T
b111001 W
1$
#3025
0$
#3050
b1110100 T
b111010 W
1$
#3075
0$
#3100
b1110110 T
b111011 W
1$
#3125
0$
#3150
b1111000 T
b111100 W
1$
#3175
0$
#3200
b1111010 T
b111101 W
1$
#3225
0$
#3250
b1111100 T
b111110 W
1$
#3275
0$
#3300
b1111110 T
b111111 W
1$
#3325
0$
#3350
b10000000 T
b1000000 W
1$
#3375
0$
#3400
b10000010 T
b1000001 W
1$
#3425
0$
#3450
b10000100 T
b1000010 W
1$
#3475
0$
#3500
b10000110 T
b1000011 W
1$
#3525
0$
#3550
b10001000 T
b1000100 W
1$
#3575
0$
#3600
b10001010 T
b1000101 W
1$
#3625
0$
#3650
b10001100 T
b1000110 W
1$
#3675
0$
#3700
b10001110 T
b1000111 W
1$
#3725
0$
#3750
b10010000 T
b1001000 W
1$
#3775
0$
#3800
b10010010 T
b1001001 W
1$
#3825
0$
#3850
b10010100 T
b1001010 W
1$
#3875
0$
#3900
b10010110 T
b1001011 W
1$
#3925
0$
#3950
b10011000 T
b1001100 W
1$
#3975
0$
#4000
b10011010 T
b1001101 W
1$
#4025
0$
#4050
b10011100 T
b1001110 W
1$
#4075
0$
#4100
b10011110 T
b1001111 W
1$
#4125
0$
#4150
b10100000 T
b1010000 W
1$
#4175
0$
#4200
b10100010 T
b1010001 W
1$
#4225
0$
#4250
b10100100 T
b1010010 W
1$
#4275
0$
#4300
b10100110 T
b1010011 W
1$
#4325
0$
#4350
b10101000 T
b1010100 W
1$
#4375
0$
#4400
b10101010 T
b1010101 W
1$
#4425
0$
#4450
b10101100 T
b1010110 W
1$
#4475
0$
#4500
b10101110 T
b1010111 W
1$
#4525
0$
#4550
b10110000 T
b1011000 W
1$
#4575
0$
#4600
b10110010 T
b1011001 W
1$
#4625
0$
#4650
b10110100 T
b1011010 W
1$
#4675
0$
#4700
b10110110 T
b1011011 W
1$
#4725
0$
#4750
b10111000 T
b1011100 W
1$
#4775
0$
#4800
b10111010 T
b1011101 W
1$
#4825
0$
#4850
b10111100 T
b1011110 W
1$
#4875
0$
#4900
b10111110 T
b1011111 W
1$
#4925
0$
#4950
b11000000 T
b1100000 W
1$
#4975
0$
#5000
b11000010 T
b1100001 W
1$
#5025
0$
#5050
b11000100 T
b1100010 W
1$
#5075
0$
#5100
b11000110 T
b1100011 W
1$
#5125
0$
#5150
b11001000 T
b1100100 W
1$
#5175
0$
#5200
b11001010 T
b1100101 W
1$
#5225
0$
#5250
b11001100 T
b1100110 W
1$
#5275
0$
#5300
b11001110 T
b1100111 W
1$
#5325
0$
#5350
b11010000 T
b1101000 W
1$
#5375
0$
#5400
b11010010 T
b1101001 W
1$
#5425
0$
#5450
b11010100 T
b1101010 W
1$
#5475
0$
#5500
b11010110 T
b1101011 W
1$
#5525
0$
#5550
b11011000 T
b1101100 W
1$
#5575
0$
#5600
b11011010 T
b1101101 W
1$
#5625
0$
#5650
b11011100 T
b1101110 W
1$
#5675
0$
#5700
b11011110 T
b1101111 W
1$
#5725
0$
#5750
b11100000 T
b1110000 W
1$
#5775
0$
#5800
b11100010 T
b1110001 W
1$
#5825
0$
#5850
b11100100 T
b1110010 W
1$
#5875
0$
#5900
b11100110 T
b1110011 W
1$
#5925
0$
#5950
b11101000 T
b1110100 W
1$
#5975
0$
#6000
b11101010 T
b1110101 W
1$
#6025
0$
#6050
b11101100 T
b1110110 W
1$
#6075
0$
#6100
b11101110 T
b1110111 W
1$
#6125
0$
#6150
b11110000 T
b1111000 W
1$
#6175
0$
#6200
b11110010 T
b1111001 W
1$
#6225
0$
#6250
b11110100 T
b1111010 W
1$
#6275
0$
#6300
b11110110 T
b1111011 W
1$
#6325
0$
#6350
b11111000 T
b1111100 W
1$
#6375
0$
#6400
b11111010 T
b1111101 W
1$
#6425
0$
#6450
b11111100 T
b1111110 W
1$
#6475
0$
#6500
b11111110 T
b1111111 W
1$
#6525
0$
#6550
b100000000 T
b10000000 W
1$
#6575
0$
#6600
b100000010 T
b10000001 W
1$
#6625
0$
#6650
b100000100 T
b10000010 W
1$
#6675
0$
#6700
b100000110 T
b10000011 W
1$
#6725
0$
#6750
b100001000 T
b10000100 W
1$
#6775
0$
#6800
b100001010 T
b10000101 W
1$
#6825
0$
#6850
b100001100 T
b10000110 W
1$
#6875
0$
#6900
b100001110 T
b10000111 W
1$
#6925
0$
#6950
b100010000 T
b10001000 W
1$
#6975
0$
#7000
b100010010 T
b10001001 W
1$
#7025
0$
#7050
b100010100 T
b10001010 W
1$
#7075
0$
#7100
b100010110 T
b10001011 W
1$
#7125
0$
#7150
b100011000 T
b10001100 W
1$
#7175
0$
#7200
b100011010 T
b10001101 W
1$
#7225
0$
#7250
b100011100 T
b10001110 W
1$
#7275
0$
#7300
b100011110 T
b10001111 W
1$
#7325
0$
#7350
b100100000 T
b10010000 W
1$
#7375
0$
#7400
b100100010 T
b10010001 W
1$
#7425
0$
#7450
b100100100 T
b10010010 W
1$
#7475
0$
#7500
b100100110 T
b10010011 W
1$
#7525
0$
#7550
b100101000 T
b10010100 W
1$
#7575
0$
#7600
b100101010 T
b10010101 W
1$
#7625
0$
#7650
b100101100 T
b10010110 W
1$
#7675
0$
#7700
b100101110 T
b10010111 W
1$
#7725
0$
#7750
b100110000 T
b10011000 W
1$
#7775
0$
#7800
b100110010 T
b10011001 W
1$
#7825
0$
#7850
b100110100 T
b10011010 W
1$
#7875
0$
#7900
b100110110 T
b10011011 W
1$
#7925
0$
#7950
b100111000 T
b10011100 W
1$
#7975
0$
#8000
b100111010 T
b10011101 W
1$
#8025
0$
#8050
b100111100 T
b10011110 W
1$
#8075
0$
#8100
b100111110 T
b10011111 W
1$
#8125
0$
#8150
b101000000 T
b10100000 W
1$
#8175
0$
#8200
b101000010 T
b10100001 W
1$
#8225
0$
#8250
b101000100 T
b10100010 W
1$
#8275
0$
#8300
b101000110 T
b10100011 W
1$
#8325
0$
#8350
b101001000 T
b10100100 W
1$
#8375
0$
#8400
b101001010 T
b10100101 W
1$
#8425
0$
#8450
b101001100 T
b10100110 W
1$
#8475
0$
#8500
b101001110 T
b10100111 W
1$
#8525
0$
#8550
b101010000 T
b10101000 W
1$
#8575
0$
#8600
b101010010 T
b10101001 W
1$
#8625
0$
#8650
b101010100 T
b10101010 W
1$
#8675
0$
#8700
b101010110 T
b10101011 W
1$
#8725
0$
#8750
b101011000 T
b10101100 W
1$
#8775
0$
#8800
b101011010 T
b10101101 W
1$
#8825
0$
#8850
b101011100 T
b10101110 W
1$
#8875
0$
#8900
b101011110 T
b10101111 W
1$
#8925
0$
#8950
b101100000 T
b10110000 W
1$
#8975
0$
#9000
b101100010 T
b10110001 W
1$
#9025
0$
#9050
b101100100 T
b10110010 W
1$
#9075
0$
#9100
b101100110 T
b10110011 W
1$
#9125
0$
#9150
b101101000 T
b10110100 W
1$
#9175
0$
#9200
b101101010 T
b10110101 W
1$
#9225
0$
#9250
b101101100 T
b10110110 W
1$
#9275
0$
#9300
b101101110 T
b10110111 W
1$
#9325
0$
#9350
b101110000 T
b10111000 W
1$
#9375
0$
#9400
b101110010 T
b10111001 W
1$
#9425
0$
#9450
b101110100 T
b10111010 W
1$
#9475
0$
#9500
b101110110 T
b10111011 W
1$
#9525
0$
#9550
b101111000 T
b10111100 W
1$
#9575
0$
#9600
b101111010 T
b10111101 W
1$
#9625
0$
#9650
b101111100 T
b10111110 W
1$
#9675
0$
#9700
b101111110 T
b10111111 W
1$
#9725
0$
#9750
b110000000 T
b11000000 W
1$
#9775
0$
#9800
b110000010 T
b11000001 W
1$
#9825
0$
#9850
b110000100 T
b11000010 W
1$
#9875
0$
#9900
b110000110 T
b11000011 W
1$
#9925
0$
#9950
b110001000 T
b11000100 W
1$
#9975
0$
#10000
b110001010 T
b11000101 W
1$
#10025
0$
#10050
b110001100 T
b11000110 W
1$
#10075
0$
#10100
b110001110 T
b11000111 W
1$
#10125
0$
#10150
b110010000 T
b11001000 W
1$
#10175
0$
#10200
b110010010 T
b11001001 W
1$
#10225
0$
#10250
b110010100 T
b11001010 W
1$
#10275
0$
#10300
b110010110 T
b11001011 W
1$
#10325
0$
#10350
b110011000 T
b11001100 W
1$
#10375
0$
#10400
b110011010 T
b11001101 W
1$
#10425
0$
#10450
b110011100 T
b11001110 W
1$
#10475
0$
#10500
b110011110 T
b11001111 W
1$
#10525
0$
#10550
b110100000 T
b11010000 W
1$
#10575
0$
#10600
b110100010 T
b11010001 W
1$
#10625
0$
#10650
b110100100 T
b11010010 W
1$
#10675
0$
#10700
b110100110 T
b11010011 W
1$
#10725
0$
#10750
b110101000 T
b11010100 W
1$
#10775
0$
#10800
b110101010 T
b11010101 W
1$
#10825
0$
#10850
b110101100 T
b11010110 W
1$
#10875
0$
#10900
b110101110 T
b11010111 W
1$
#10925
0$
#10950
b110110000 T
b11011000 W
1$
#10975
0$
#11000
b110110010 T
b11011001 W
1$
#11025
0$
#11050
b110110100 T
b11011010 W
1$
#11075
0$
#11100
b110110110 T
b11011011 W
1$
#11125
0$
#11150
b110111000 T
b11011100 W
1$
#11175
0$
#11200
b110111010 T
b11011101 W
1$
#11225
0$
#11250
b110111100 T
b11011110 W
1$
#11275
0$
#11300
b110111110 T
b11011111 W
1$
#11325
0$
#11350
b111000000 T
b11100000 W
1$
#11375
0$
#11400
b111000010 T
b11100001 W
1$
#11425
0$
#11450
b111000100 T
b11100010 W
1$
#11475
0$
#11500
b111000110 T
b11100011 W
1$
#11525
0$
#11550
b111001000 T
b11100100 W
1$
#11575
0$
#11600
b111001010 T
b11100101 W
1$
#11625
0$
#11650
b111001100 T
b11100110 W
1$
#11675
0$
#11700
b111001110 T
b11100111 W
1$
#11725
0$
#11750
b111010000 T
b11101000 W
1$
#11775
0$
#11800
b111010010 T
b11101001 W
1$
#11825
0$
#11850
b111010100 T
b11101010 W
1$
#11875
0$
#11900
b111010110 T
b11101011 W
1$
#11925
0$
#11950
b111011000 T
b11101100 W
1$
#11975
0$
#12000
b111011010 T
b11101101 W
1$
#12025
0$
#12050
b111011100 T
b11101110 W
1$
#12075
0$
#12100
b111011110 T
b11101111 W
1$
#12125
0$
#12150
b111100000 T
b11110000 W
1$
#12175
0$
#12200
b111100010 T
b11110001 W
1$
#12225
0$
#12250
b111100100 T
b11110010 W
1$
#12275
0$
#12300
b111100110 T
b11110011 W
1$
#12325
0$
#12350
b111101000 T
b11110100 W
1$
#12375
0$
#12400
b111101010 T
b11110101 W
1$
#12425
0$
#12450
b111101100 T
b11110110 W
1$
#12475
0$
#12500
b111101110 T
b11110111 W
1$
#12525
0$
#12550
b111110000 T
b11111000 W
1$
#12575
0$
#12600
b111110010 T
b11111001 W
1$
#12625
0$
#12650
b111110100 T
b11111010 W
1$
#12675
0$
#12700
b111110110 T
b11111011 W
1$
#12725
0$
#12750
b111111000 T
b11111100 W
1$
#12775
0$
#12800
b111111010 T
b11111101 W
1$
#12825
0$
#12850
b111111100 T
b11111110 W
1$
#12875
0$
#12900
b111111110 T
b11111111 W
1$
#12925
0$
#12950
b1000000000 T
b100000000 W
1$
#12975
0$
#13000
b1000000010 T
b100000001 W
1$
#13025
0$
#13050
b1000000100 T
b100000010 W
1$
#13075
0$
#13100
b1000000110 T
b100000011 W
1$
#13125
0$
#13150
b1000001000 T
b100000100 W
1$
#13175
0$
#13200
b1000001010 T
b100000101 W
1$
#13225
0$
#13250
b1000001100 T
b100000110 W
1$
#13275
0$
#13300
b1000001110 T
b100000111 W
1$
#13325
0$
#13350
b1000010000 T
b100001000 W
1$
#13375
0$
#13400
b1000010010 T
b100001001 W
1$
#13425
0$
#13450
b1000010100 T
b100001010 W
1$
#13475
0$
#13500
b1000010110 T
b100001011 W
1$
#13525
0$
#13550
b1000011000 T
b100001100 W
1$
#13575
0$
#13600
b1000011010 T
b100001101 W
1$
#13625
0$
#13650
b1000011100 T
b100001110 W
1$
#13675
0$
#13700
b1000011110 T
b100001111 W
1$
#13725
0$
#13750
b1000100000 T
b100010000 W
1$
#13775
0$
#13800
b1000100010 T
b100010001 W
1$
#13825
0$
#13850
b1000100100 T
b100010010 W
1$
#13875
0$
#13900
b1000100110 T
b100010011 W
1$
#13925
0$
#13950
b1000101000 T
b100010100 W
1$
#13975
0$
#14000
b1000101010 T
b100010101 W
1$
#14025
0$
#14050
b1000101100 T
b100010110 W
1$
#14075
0$
#14100
b1000101110 T
b100010111 W
1$
#14125
0$
#14150
b1000110000 T
b100011000 W
1$
#14175
0$
#14200
b1000110010 T
b100011001 W
1$
#14225
0$
#14250
b1000110100 T
b100011010 W
1$
#14275
0$
#14300
b1000110110 T
b100011011 W
1$
#14325
0$
#14350
b1000111000 T
b100011100 W
1$
#14375
0$
#14400
b1000111010 T
b100011101 W
1$
#14425
0$
#14450
b1000111100 T
b100011110 W
1$
#14475
0$
#14500
b1000111110 T
b100011111 W
1$
#14525
0$
#14550
b1001000000 T
b100100000 W
1$
#14575
0$
#14600
b1001000010 T
b100100001 W
1$
#14625
0$
#14650
b1001000100 T
b100100010 W
1$
#14675
0$
#14700
b1001000110 T
b100100011 W
1$
#14725
0$
#14750
b1001001000 T
b100100100 W
1$
#14775
0$
#14800
b1001001010 T
b100100101 W
1$
#14825
0$
#14850
b1001001100 T
b100100110 W
1$
#14875
0$
#14900
b1001001110 T
b100100111 W
1$
#14925
0$
#14950
b1001010000 T
b100101000 W
1$
#14975
0$
#15000
b1001010010 T
b100101001 W
1$
#15025
0$
#15050
b1001010100 T
b100101010 W
1$
#15075
0$
#15100
b1001010110 T
b100101011 W
1$
#15125
0$
#15150
b1001011000 T
b100101100 W
1$
#15175
0$
#15200
b1001011010 T
b100101101 W
1$
#15225
0$
#15250
b1001011100 T
b100101110 W
1$
#15275
0$
#15300
b1001011110 T
b100101111 W
1$
#15325
0$
#15350
b1001100000 T
b100110000 W
1$
#15375
0$
#15400
b1001100010 T
b100110001 W
1$
#15425
0$
#15450
b1001100100 T
b100110010 W
1$
#15475
0$
#15500
b1001100110 T
b100110011 W
1$
#15525
0$
#15550
b1001101000 T
b100110100 W
1$
#15575
0$
