verilog/nakahara/SEQUENCER_DEF_new.v
`define INST_WBUF_SEND      0
`define INST_COUNTER0_S     1
`define INST_COUNTER0_E     8
`define INST_WBUF_EN_CTRL_S 9
`define INST_WBUF_EN_CTRL_E 14
`define INST_RADDRX_WE      15
`define INST_RADDRX_S       16 
`define INST_RADDRX_E       31

verilog/exe/wbuf_send.v
module wbuf_send(
	input wire CLK, 
	input wire RSTL,
	input wire WBUF_SEND,
	input wire [7:0] COUNTER0,
	input wire [5:0] WBUF_EN_CTRL_I,
	output wire [15:0] RADDRX,
	output wire RCEBX,
	output wire WBUF_EN,
	output wire [5:0] WBUF_EN_CTRL,
	output wire WBUF_BUSY
	);

	reg [15:0] 	pc;
	reg [2:0]   cnt;
	reg [7:0] 	counter0;
	reg [15:0] 	reg_raddrx;
	reg			reg_rcebx;
	reg 		reg_wbufen;
	reg [5:0]  	reg_wbufenctrl;


	assign RADDRX = reg_raddrx;
	assign WBUF_EN_CTRL = reg_wbufenctrl;
	assign WBUF_BUSY = (counter0 > 1 | |cnt) ? 1:0;
	assign RCEBX   = ~|counter0;
	assign WBUF_EN = |counter0;

	//counter0
  	always @(posedge CLK or negedge RSTL)  begin
		if (!RSTL) begin
			counter0 <= 0;
		end
		else if(WBUF_SEND && !WBUF_BUSY) begin
			counter0 <= COUNTER0;
		end
		else if(|counter0 && cnt == 3'b0) begin
			counter0 <= counter0 - 1;
		end
		else begin
			counter0 <= counter0;
		end
	end

	//cnt:アドレス用カウンタ
  	always @(posedge CLK or negedge RSTL) begin
		if (!RSTL)	
			cnt <= 0;
		else if(WBUF_SEND & !WBUF_BUSY)
			cnt <= 3'b100;
		else if(WBUF_BUSY && ~|cnt)
			cnt <= 3'b011;
		else if(WBUF_BUSY) begin
			cnt <= cnt - 1;
		end else
			cnt <= 0;
	end

	//RADDRX
	always @(posedge CLK or negedge RSTL) begin
		if (!RSTL)			
			reg_raddrx <= 1'd0;
		else if(WBUF_BUSY)
			reg_raddrx <= reg_raddrx + 1'd1;
		else
			reg_raddrx <= reg_raddrx;
    end

	//WBUF_EN_CTRL
	always@ (posedge CLK or negedge RSTL) begin
		if (!RSTL)       
			reg_wbufenctrl <= 1'd0;
		else if(WBUF_SEND & !WBUF_BUSY)
			reg_wbufenctrl <= WBUF_EN_CTRL_I;
		else if(WBUF_BUSY & ~|cnt)
			reg_wbufenctrl <= reg_wbufenctrl + 1'd1;
		else
			reg_wbufenctrl <= reg_wbufenctrl;
	end


endmodule

verilog/nakahara/SEQUENCER_new.v
`include "SEQUENCER_DEF_new.v"

module SEQUENCER (input wire CLK,
                  input wire RSTL,
                  input wire PURGE,
                  input wire MBUSYW,
                  input wire MBUSYXI,
                  input wire MBUSYXO,
                  input wire [255:0] QI,
                  output wire [15:0] RADDRI,
                  output wire RCEBI,
                  output wire [15:0] RADDRX,
                  output wire [15:0] RADDRW,
                  output wire [15:0] WADDRX,
                  output wire BANKX,
                  output wire BANKW,
                  output wire RCEBW,
                  output wire RCEBX,
                  output wire WCEBX,
                  output wire REQW,
                  output wire WBUF_PURGE,
                  output wire WBUF_EN,
                  output wire [5:0] WBUF_EN_CTRL,
                  output wire WBUF_ALL_EN,
                  output wire WBUF_SWITCH,
                  output wire FC_WEIGHT_EN,
                  output wire NL_EN,
                  output wire SHIFT_MODE,
                  output wire [1:0] NL_SEL,
                  output wire MAC_EN,
                  output wire RESULT_REQ,
                  output wire [3:0] OLSB,
                  output wire RESULT_PURGE,
                  output wire OUTPUT_EN,
                  output wire [5:0] OUTPUT_EN_CTRL,
                  output wire I_COMPARE_EN,
                  output wire I_COMPARE_MODE,
                  output wire I_COMPARE_SWITCH,
                  output wire O_COMPARE_EN,
                  output wire O_COMPARE_MODE,
                  output wire O_COMPARE_SWITCH,
                  output wire CAL_MODE,
                  output wire CONV_FC_MODE,
                  output wire FEEDBACK_MODE,
                  output wire CONF_EN,
                  output wire I_COMPARE_REGEN,
                  output wire [1:0] NL_LOOP_SEL,
                  output wire SEQ_LOAD_I,
                  output wire SEQ_FIN,
                  output wire SEQ_STARTW,
                  output wire SEQ_STARTX,
                  output wire SEQ_STARTX_OUT,
                  output wire RCEBX0);
    
    reg [15:0] pc; //SRAM（マイクロコード）の何行目からもってくるか
    reg [7:0] counter1; //ループ回数
    reg [7:0] counter2; //ループ回数
    reg [7:0] counter3; //ループ回数
    reg [15:0] reg_raddrx; //SRAMからの読み取りアドレス
    reg [15:0] reg_waddrx; //SRAMアドレス
    reg [15:0] reg_raddrw;
    reg [15:0] reg_raddrx_bak;
    reg [15:0] reg_raddrw_bak;
    reg [5:0]  reg_wbufenctrl;
    reg [5:0]  reg_outputenctrl;
    reg        reg_switch;
    reg [15:0] reg_raddrx_latch;
    reg [15:0] reg_waddrx_latch;
    reg [15:0] reg_raddrw_latch;
    reg [5:0]  reg_wbufenctrl_latch;
    reg [5:0]  reg_outputenctrl_latch;
    reg        reg_switch_latch;
    reg [255:0] qi_latch;
    wire [7:0] counter_end;
    reg [2:0] cnt;
    reg [7:0] counter;
    wire [15:0] counter_en;
    wire module_busy;
    wire wbuf_busy;
    wire module_en;
    reg  pc_adjust;

    assign RADDRI = {pc[14:0],1'b0};
    assign RCEBI  = 1'b0;
    assign counter_en = QI[`INST_COUNTER0_E:`INST_COUNTER0_S];
    assign module_busy = wbuf_busy;
    assign module_en = QI[`INST_WBUF_SEND];

    //PC
    always@ (posedge CLK or negedge RSTL)
    begin
        if (!RSTL)                          pc <= 16'b0;
        else if (PURGE)                     pc <= 16'b0;
        else if (module_busy)               pc <= pc;
        else if (!pc_adjust & module_en)    pc <= pc;
        else                                pc <= pc + 1'b1;
    end
    
    //pc_adjust
    always@ (posedge CLK or negedge RSTL)
    begin
        if (!RSTL)      pc_adjust <= 0;
        else if (PURGE) pc_adjust <= 0;
        else            pc_adjust <= module_busy;
    end

    //RADDRX
    wire [15:0] raddrx;
    assign raddrx = reg_raddrx;
    always@ (posedge CLK or negedge RSTL)
    begin
        if (!RSTL)       reg_raddrx <= 16'b0;
        else if (PURGE)  reg_raddrx <= 16'b0;
        else begin
            case(QI[`INST_RADDRX_WE])
                1'b0:
                    case(QI[`INST_RADDRX_E])
                        1'b0:
                            reg_raddrx <= reg_raddrx + QI[`INST_RADDRX_E - 1:`INST_RADDRX_S];
                        1'b1:
                            reg_raddrx <= reg_raddrx - QI[`INST_RADDRX_E - 1:`INST_RADDRX_S];
                    endcase
                1'b1:
                    reg_raddrx <= QI[`INST_RADDRX_E:`INST_RADDRX_S];
            endcase
        end
    end

    //命令モジュール呼び出し //.下位input(上位input) or .下位output(上位output)
    wbuf_send wbuf_send_0(
        //input
        .CLK(CLK),
        .RSTL(RSTL),
        .WBUF_SEND(QI[`INST_WBUF_SEND]),
        .COUNTER0(QI[`INST_COUNTER0_E:`INST_COUNTER0_S]),
        .WBUF_EN_CTRL_I(QI[`INST_WBUF_EN_CTRL_E:`INST_WBUF_EN_CTRL_S]),
        //output
        .RADDRX(RADDRX),
        .RCEBX(RCEBX),
        .WBUF_EN(WBUF_EN),
        .WBUF_EN_CTRL(WBUF_EN_CTRL),
        .WBUF_BUSY(wbuf_busy)
    );

endmodule

verilog/nakahara/sequencer_new_test.v
`timescale	100ps/100ps

module sequencer_test;

parameter STEP = 50;

reg clk,rstn,purge;
reg [255:0] q;
wire [15:0] a;
wire [15:0] pc;
wire ceb;
reg [255:0] memory [0:100];
reg [255:0] d;

always begin
    clk = 1; #(STEP/2);
    clk = 0; #(STEP/2);
end

always @(posedge clk) begin
    if (!ceb) q <= memory[{2'b0,a[14:1]}];
    else q <= 255'b0;
end

SEQUENCER SEQUENCER_0(
.CLK(clk),
.RSTL(rstn),
.PURGE(purge),
.QI(q),
.RADDRI(a),
.RCEBI(ceb)
);

initial begin
    $dumpfile("sequencer_new_test.vcd");
    $dumpvars(0,SEQUENCER_0);
    $readmemb("memfile.dat", memory);

    rstn = 0;
    purge = 0;

    #(STEP * 2 + 1)
                rstn = 1;

    #STEP
                purge = 0;

    #(STEP * 20000) 
            $dumpflush;
    #STEP   $finish;

end

endmodule

verilog/nakahara/sequencer_new_test.vcd
$date
	Thu Jan 21 14:39:09 2021
$end
$version
	Icarus Verilog
$end
$timescale
	100ps
$end
$scope module sequencer_test $end
$scope module SEQUENCER_0 $end
$var wire 1 ! BANKW $end
$var wire 1 " BANKX $end
$var wire 1 # CAL_MODE $end
$var wire 1 $ CLK $end
$var wire 1 % CONF_EN $end
$var wire 1 & CONV_FC_MODE $end
$var wire 1 ' FC_WEIGHT_EN $end
$var wire 1 ( FEEDBACK_MODE $end
$var wire 1 ) I_COMPARE_EN $end
$var wire 1 * I_COMPARE_MODE $end
$var wire 1 + I_COMPARE_REGEN $end
$var wire 1 , I_COMPARE_SWITCH $end
$var wire 1 - MAC_EN $end
$var wire 1 . MBUSYW $end
$var wire 1 / MBUSYXI $end
$var wire 1 0 MBUSYXO $end
$var wire 1 1 NL_EN $end
$var wire 2 2 NL_LOOP_SEL [1:0] $end
$var wire 2 3 NL_SEL [1:0] $end
$var wire 4 4 OLSB [3:0] $end
$var wire 1 5 OUTPUT_EN $end
$var wire 6 6 OUTPUT_EN_CTRL [5:0] $end
$var wire 1 7 O_COMPARE_EN $end
$var wire 1 8 O_COMPARE_MODE $end
$var wire 1 9 O_COMPARE_SWITCH $end
$var wire 1 : PURGE $end
$var wire 256 ; QI [255:0] $end
$var wire 16 < RADDRW [15:0] $end
$var wire 1 = RCEBI $end
$var wire 1 > RCEBW $end
$var wire 1 ? RCEBX0 $end
$var wire 1 @ REQW $end
$var wire 1 A RESULT_PURGE $end
$var wire 1 B RESULT_REQ $end
$var wire 1 C RSTL $end
$var wire 1 D SEQ_FIN $end
$var wire 1 E SEQ_LOAD_I $end
$var wire 1 F SEQ_STARTW $end
$var wire 1 G SEQ_STARTX $end
$var wire 1 H SEQ_STARTX_OUT $end
$var wire 1 I SHIFT_MODE $end
$var wire 16 J WADDRX [15:0] $end
$var wire 1 K WBUF_ALL_EN $end
$var wire 1 L WBUF_PURGE $end
$var wire 1 M WBUF_SWITCH $end
$var wire 1 N WCEBX $end
$var wire 1 O module_busy $end
$var wire 16 P raddrx [15:0] $end
$var wire 1 Q wbuf_busy $end
$var wire 1 R module_en $end
$var wire 16 S counter_en [15:0] $end
$var wire 6 T WBUF_EN_CTRL [5:0] $end
$var wire 1 U WBUF_EN $end
$var wire 1 V RCEBX $end
$var wire 16 W RADDRX [15:0] $end
$var wire 16 X RADDRI [15:0] $end
$var reg 16 Y pc [15:0] $end
$var reg 1 Z pc_adjust $end
$var reg 16 [ reg_raddrx [15:0] $end
$scope module wbuf_send_0 $end
$var wire 1 $ CLK $end
$var wire 8 \ COUNTER0 [7:0] $end
$var wire 16 ] RADDRX [15:0] $end
$var wire 1 C RSTL $end
$var wire 6 ^ WBUF_EN_CTRL [5:0] $end
$var wire 6 _ WBUF_EN_CTRL_I [5:0] $end
$var wire 1 ` WBUF_SEND $end
$var wire 1 U WBUF_EN $end
$var wire 1 Q WBUF_BUSY $end
$var wire 1 V RCEBX $end
$var reg 3 a cnt [2:0] $end
$var reg 8 b counter0 [7:0] $end
$var reg 16 c reg_raddrx [15:0] $end
$var reg 6 d reg_wbufenctrl [5:0] $end
$upscope $end
$upscope $end
$upscope $end
$enddefinitions $end
#0
$dumpvars
b0 d
b0 c
b0 b
b0 a
x`
bx _
b0 ^
b0 ]
bx \
b0 [
0Z
b0 Y
b0 X
b0 W
1V
0U
b0 T
b0xxxxxxxx S
xR
0Q
b0 P
0O
zN
zM
zL
zK
bz J
zI
zH
zG
zF
zE
zD
0C
zB
zA
z@
z?
z>
0=
bz <
bx ;
0:
z9
z8
z7
bz 6
z5
bz 4
bz 3
bz 2
z1
z0
z/
z.
z-
z,
z+
z*
z)
z(
z'
z&
z%
1$
z#
z"
z!
$end
#25
0$
#50
b0 S
0R
0`
b0 \
b0 _
b1001000000000000000 ;
1$
#75
0$
#100
1$
#101
1C
#125
0$
#150
b10 X
b100 P
b100 [
b1 Y
1$
#175
0$
#200
b100 X
b100 S
1R
1`
b100 \
b10 Y
b1001 ;
1$
#225
0$
#250
1O
1Q
b0 S
0R
0`
b0 \
b100 a
0V
1U
b100 b
b0 ;
1$
#275
0$
#300
b11 a
b1 W
b1 ]
b1 c
1Z
1$
#325
0$
#350
b10 W
b10 ]
b10 c
b10 a
1$
#375
0$
#400
b1 a
b11 W
b11 ]
b11 c
1$
#425
0$
#450
b100 W
b100 ]
b100 c
b0 a
1$
#475
0$
#500
b11 b
b11 a
b101 W
b101 ]
b101 c
b1 T
b1 ^
b1 d
1$
#525
0$
#550
b110 W
b110 ]
b110 c
b10 a
1$
#575
0$
#600
b1 a
b111 W
b111 ]
b111 c
1$
#625
0$
#650
b1000 W
b1000 ]
b1000 c
b0 a
1$
#675
0$
#700
b10 b
b11 a
b1001 W
b1001 ]
b1001 c
b10 T
b10 ^
b10 d
1$
#725
0$
#750
b1010 W
b1010 ]
b1010 c
b10 a
1$
#775
0$
#800
b1 a
b1011 W
b1011 ]
b1011 c
1$
#825
0$
#850
b1100 W
b1100 ]
b1100 c
b0 a
1$
#875
0$
#900
b1 b
b11 a
b1101 W
b1101 ]
b1101 c
b11 T
b11 ^
b11 d
1$
#925
0$
#950
b1110 W
b1110 ]
b1110 c
b10 a
1$
#975
0$
#1000
b1 a
b1111 W
b1111 ]
b1111 c
1$
#1025
0$
#1050
0O
0Q
b10000 W
b10000 ]
b10000 c
b0 a
1$
#1075
0$
#1100
b110 X
1V
0U
b0 b
b11 Y
0Z
1$
#1125
0$
#1150
b1000 X
b100 S
1R
1`
b100 \
b100 Y
b1001 ;
1$
#1175
0$
#1200
1O
1Q
0R
0`
0V
1U
b100 b
b100 a
b0 T
b0 ^
b0 d
b1000 ;
1$
#1225
0$
#1250
1Z
b10001 W
b10001 ]
b10001 c
b11 a
1$
#1275
0$
#1300
b10 a
b10010 W
b10010 ]
b10010 c
1$
#1325
0$
#1350
b10011 W
b10011 ]
b10011 c
b1 a
1$
#1375
0$
#1400
b0 a
b10100 W
b10100 ]
b10100 c
1$
#1425
0$
#1450
b1 T
b1 ^
b1 d
b10101 W
b10101 ]
b10101 c
b11 a
b11 b
1$
#1475
0$
#1500
b10 a
b10110 W
b10110 ]
b10110 c
1$
#1525
0$
#1550
b10111 W
b10111 ]
b10111 c
b1 a
1$
#1575
0$
#1600
b0 a
b11000 W
b11000 ]
b11000 c
1$
#1625
0$
#1650
b10 T
b10 ^
b10 d
b11001 W
b11001 ]
b11001 c
b11 a
b10 b
1$
#1675
0$
#1700
b10 a
b11010 W
b11010 ]
b11010 c
1$
#1725
0$
#1750
b11011 W
b11011 ]
b11011 c
b1 a
1$
#1775
0$
#1800
b0 a
b11100 W
b11100 ]
b11100 c
1$
#1825
0$
#1850
b11 T
b11 ^
b11 d
b11101 W
b11101 ]
b11101 c
b11 a
b1 b
1$
#1875
0$
#1900
b10 a
b11110 W
b11110 ]
b11110 c
1$
#1925
0$
#1950
b11111 W
b11111 ]
b11111 c
b1 a
1$
#1975
0$
#2000
0O
0Q
b0 a
b100000 W
b100000 ]
b100000 c
1$
#2025
0$
#2050
b1010 X
0Z
b101 Y
1V
0U
b0 b
1$
#2075
0$
#2100
b1100 X
b110 Y
1$
#2125
0$
#2150
b1110 X
b111 Y
1$
#2175
0$
#2200
b10000 X
b1000 Y
1$
#2225
0$
#2250
b10010 X
b1001 Y
1$
#2275
0$
#2300
b10100 X
b0xxxxxxxx S
xR
x`
bx \
bx _
b1010 Y
bx ;
1$
#2325
0$
#2350
b10110 X
b1011 Y
1$
#2375
0$
#2400
b11000 X
b1100 Y
1$
#2425
0$
#2450
b11010 X
b1101 Y
1$
#2475
0$
#2500
b11100 X
b1110 Y
1$
#2525
0$
#2550
b11110 X
b1111 Y
1$
#2575
0$
#2600
b100000 X
b10000 Y
1$
#2625
0$
#2650
b100010 X
b10001 Y
1$
#2675
0$
#2700
b100100 X
b10010 Y
1$
#2725
0$
#2750
b100110 X
b10011 Y
1$
#2775
0$
#2800
b101000 X
b10100 Y
1$
#2825
0$
#2850
b101010 X
b10101 Y
1$
#2875
0$
#2900
b101100 X
b10110 Y
1$
#2925
0$
#2950
b101110 X
b10111 Y
1$
#2975
0$
#3000
b110000 X
b11000 Y
1$
#3025
0$
#3050
b110010 X
b11001 Y
1$
#3075
0$
#3100
b110100 X
b11010 Y
1$
#3125
0$
#3150
b110110 X
b11011 Y
1$
#3175
0$
#3200
b111000 X
b11100 Y
1$
#3225
0$
#3250
b111010 X
b11101 Y
1$
#3275
0$
#3300
b111100 X
b11110 Y
1$
#3325
0$
#3350
b111110 X
b11111 Y
1$
#3375
0$
#3400
b1000000 X
b100000 Y
1$
#3425
0$
#3450
b1000010 X
b100001 Y
1$
#3475
0$
#3500
b1000100 X
b100010 Y
1$
#3525
0$
#3550
b1000110 X
b100011 Y
1$
#3575
0$
#3600
b1001000 X
b100100 Y
1$
#3625
0$
#3650
b1001010 X
b100101 Y
1$
#3675
0$
#3700
b1001100 X
b100110 Y
1$
#3725
0$
#3750
b1001110 X
b100111 Y
1$
#3775
0$
#3800
b1010000 X
b101000 Y
1$
#3825
0$
#3850
b1010010 X
b101001 Y
1$
#3875
0$
#3900
b1010100 X
b101010 Y
1$
#3925
0$
#3950
b1010110 X
b101011 Y
1$
#3975
0$
#4000
b1011000 X
b101100 Y
1$
#4025
0$
#4050
b1011010 X
b101101 Y
1$
#4075
0$
#4100
b1011100 X
b101110 Y
1$
#4125
0$
#4150
b1011110 X
b101111 Y
1$
#4175
0$
#4200
b1100000 X
b110000 Y
1$
#4225
0$
#4250
b1100010 X
b110001 Y
1$
#4275
0$
#4300
b1100100 X
b110010 Y
1$
#4325
0$
#4350
b1100110 X
b110011 Y
1$
#4375
0$
#4400
b1101000 X
b110100 Y
1$
#4425
0$
#4450
b1101010 X
b110101 Y
1$
#4475
0$
#4500
b1101100 X
b110110 Y
1$
#4525
0$
#4550
b1101110 X
b110111 Y
1$
#4575
0$
#4600
b1110000 X
b111000 Y
1$
#4625
0$
#4650
b1110010 X
b111001 Y
1$
#4675
0$
#4700
b1110100 X
b111010 Y
1$
#4725
0$
#4750
b1110110 X
b111011 Y
1$
#4775
0$
#4800
b1111000 X
b111100 Y
1$
#4825
0$
#4850
b1111010 X
b111101 Y
1$
#4875
0$
#4900
b1111100 X
b111110 Y
1$
#4925
0$
#4950
b1111110 X
b111111 Y
1$
#4975
0$
#5000
b10000000 X
b1000000 Y
1$
#5025
0$
#5050
b10000010 X
b1000001 Y
1$
#5075
0$
#5100
b10000100 X
b1000010 Y
1$
#5125
0$
#5150
b10000110 X
b1000011 Y
1$
#5175
0$
#5200
b10001000 X
b1000100 Y
1$
#5225
0$
#5250
b10001010 X
b1000101 Y
1$
#5275
0$
#5300
b10001100 X
b1000110 Y
1$
#5325
0$
#5350
b10001110 X
b1000111 Y
1$
#5375
0$
#5400
b10010000 X
b1001000 Y
1$
#5425
0$
#5450
b10010010 X
b1001001 Y
1$
#5475
0$
#5500
b10010100 X
b1001010 Y
1$
#5525
0$
#5550
b10010110 X
b1001011 Y
1$
#5575
0$
#5600
b10011000 X
b1001100 Y
1$
#5625
0$
#5650
b10011010 X
b1001101 Y
1$
#5675
0$
#5700
b10011100 X
b1001110 Y
1$
#5725
0$
#5750
b10011110 X
b1001111 Y
1$
#5775
0$
#5800
b10100000 X
b1010000 Y
1$
#5825
0$
#5850
b10100010 X
b1010001 Y
1$
#5875
0$
#5900
b10100100 X
b1010010 Y
1$
#5925
0$
#5950
b10100110 X
b1010011 Y
1$
#5975
0$
#6000
b10101000 X
b1010100 Y
1$
#6025
0$
#6050
b10101010 X
b1010101 Y
1$
#6075
0$
#6100
b10101100 X
b1010110 Y
1$
#6125
0$
#6150
b10101110 X
b1010111 Y
1$
#6175
0$
#6200
b10110000 X
b1011000 Y
1$
#6225
0$
#6250
b10110010 X
b1011001 Y
1$
#6275
0$
#6300
b10110100 X
b1011010 Y
1$
#6325
0$
#6350
b10110110 X
b1011011 Y
1$
#6375
0$
#6400
b10111000 X
b1011100 Y
1$
#6425
0$
#6450
b10111010 X
b1011101 Y
1$
#6475
0$
#6500
b10111100 X
b1011110 Y
1$
#6525
0$
#6550
b10111110 X
b1011111 Y
1$
#6575
0$
#6600
b11000000 X
b1100000 Y
1$
#6625
0$
#6650
b11000010 X
b1100001 Y
1$
#6675
0$
#6700
b11000100 X
b1100010 Y
1$
#6725
0$
#6750
b11000110 X
b1100011 Y
1$
#6775
0$
#6800
b11001000 X
b1100100 Y
1$
#6825
0$
#6850
b11001010 X
b1100101 Y
1$
#6875
0$
#6900
b11001100 X
b1100110 Y
1$
#6925
0$
#6950
b11001110 X
b1100111 Y
1$
#6975
0$
#7000
b11010000 X
b1101000 Y
1$
#7025
0$
#7050
b11010010 X
b1101001 Y
1$
#7075
0$
#7100
b11010100 X
b1101010 Y
1$
#7125
0$
#7150
b11010110 X
b1101011 Y
1$
#7175
0$
#7200
b11011000 X
b1101100 Y
1$
#7225
0$
#7250
b11011010 X
b1101101 Y
1$
#7275
0$
#7300
b11011100 X
b1101110 Y
1$
#7325
0$
#7350
b11011110 X
b1101111 Y
1$
#7375
0$
#7400
b11100000 X
b1110000 Y
1$
#7425
0$
#7450
b11100010 X
b1110001 Y
1$
#7475
0$
#7500
b11100100 X
b1110010 Y
1$
#7525
0$
#7550
b11100110 X
b1110011 Y
1$
#7575
0$
#7600
b11101000 X
b1110100 Y
1$
#7625
0$
#7650
b11101010 X
b1110101 Y
1$
#7675
0$
#7700
b11101100 X
b1110110 Y
1$
#7725
0$
#7750
b11101110 X
b1110111 Y
1$
#7775
0$
#7800
b11110000 X
b1111000 Y
1$
#7825
0$
#7850
b11110010 X
b1111001 Y
1$
#7875
0$
#7900
b11110100 X
b1111010 Y
1$
#7925
0$
#7950
b11110110 X
b1111011 Y
1$
#7975
0$
#8000
b11111000 X
b1111100 Y
1$
#8025
0$
#8050
b11111010 X
b1111101 Y
1$
#8075
0$
#8100
b11111100 X
b1111110 Y
1$
#8125
0$
#8150
b11111110 X
b1111111 Y
1$
#8175
0$
#8200
b100000000 X
b10000000 Y
1$
#8225
0$
#8250
b100000010 X
b10000001 Y
1$
#8275
0$
#8300
b100000100 X
b10000010 Y
1$
#8325
0$
#8350
b100000110 X
b10000011 Y
1$
#8375
0$
#8400
b100001000 X
b10000100 Y
1$
#8425
0$
#8450
b100001010 X
b10000101 Y
1$
#8475
0$
#8500
b100001100 X
b10000110 Y
1$
#8525
0$
#8550
b100001110 X
b10000111 Y
1$
#8575
0$
#8600
b100010000 X
b10001000 Y
1$
#8625
0$
#8650
b100010010 X
b10001001 Y
1$
#8675
0$
#8700
b100010100 X
b10001010 Y
1$
#8725
0$
#8750
b100010110 X
b10001011 Y
1$
#8775
0$
#8800
b100011000 X
b10001100 Y
1$
#8825
0$
#8850
b100011010 X
b10001101 Y
1$
#8875
0$
#8900
b100011100 X
b10001110 Y
1$
#8925
0$
#8950
b100011110 X
b10001111 Y
1$
#8975
0$
#9000
b100100000 X
b10010000 Y
1$
#9025
0$
#9050
b100100010 X
b10010001 Y
1$
#9075
0$
#9100
b100100100 X
b10010010 Y
1$
#9125
0$
#9150
b100100110 X
b10010011 Y
1$
#9175
0$
#9200
b100101000 X
b10010100 Y
1$
#9225
0$
#9250
b100101010 X
b10010101 Y
1$
#9275
0$
#9300
b100101100 X
b10010110 Y
1$
#9325
0$
#9350
b100101110 X
b10010111 Y
1$
#9375
0$
#9400
b100110000 X
b10011000 Y
1$
#9425
0$
#9450
b100110010 X
b10011001 Y
1$
#9475
0$
#9500
b100110100 X
b10011010 Y
1$
#9525
0$
#9550
b100110110 X
b10011011 Y
1$
#9575
0$
#9600
b100111000 X
b10011100 Y
1$
#9625
0$
#9650
b100111010 X
b10011101 Y
1$
#9675
0$
#9700
b100111100 X
b10011110 Y
1$
#9725
0$
#9750
b100111110 X
b10011111 Y
1$
#9775
0$
#9800
b101000000 X
b10100000 Y
1$
#9825
0$
#9850
b101000010 X
b10100001 Y
1$
#9875
0$
#9900
b101000100 X
b10100010 Y
1$
#9925
0$
#9950
b101000110 X
b10100011 Y
1$
#9975
0$
#10000
b101001000 X
b10100100 Y
1$
#10025
0$
#10050
b101001010 X
b10100101 Y
1$
#10075
0$
#10100
b101001100 X
b10100110 Y
1$
#10125
0$
#10150
b101001110 X
b10100111 Y
1$
#10175
0$
#10200
b101010000 X
b10101000 Y
1$
#10225
0$
#10250
b101010010 X
b10101001 Y
1$
#10275
0$
#10300
b101010100 X
b10101010 Y
1$
#10325
0$
#10350
b101010110 X
b10101011 Y
1$
#10375
0$
#10400
b101011000 X
b10101100 Y
1$
#10425
0$
#10450
b101011010 X
b10101101 Y
1$
#10475
0$
#10500
b101011100 X
b10101110 Y
1$
#10525
0$
#10550
b101011110 X
b10101111 Y
1$
#10575
0$
#10600
b101100000 X
b10110000 Y
1$
#10625
0$
#10650
b101100010 X
b10110001 Y
1$
#10675
0$
#10700
b101100100 X
b10110010 Y
1$
#10725
0$
#10750
b101100110 X
b10110011 Y
1$
#10775
0$
#10800
b101101000 X
b10110100 Y
1$
#10825
0$
#10850
b101101010 X
b10110101 Y
1$
#10875
0$
#10900
b101101100 X
b10110110 Y
1$
#10925
0$
#10950
b101101110 X
b10110111 Y
1$
#10975
0$
#11000
b101110000 X
b10111000 Y
1$
#11025
0$
#11050
b101110010 X
b10111001 Y
1$
#11075
0$
#11100
b101110100 X
b10111010 Y
1$
#11125
0$
#11150
b101110110 X
b10111011 Y
1$
#11175
0$
#11200
b101111000 X
b10111100 Y
1$
#11225
0$
#11250
b101111010 X
b10111101 Y
1$
#11275
0$
#11300
b101111100 X
b10111110 Y
1$
#11325
0$
#11350
b101111110 X
b10111111 Y
1$
#11375
0$
#11400
b110000000 X
b11000000 Y
1$
#11425
0$
#11450
b110000010 X
b11000001 Y
1$
#11475
0$
#11500
b110000100 X
b11000010 Y
1$
#11525
0$
#11550
b110000110 X
b11000011 Y
1$
#11575
0$
#11600
b110001000 X
b11000100 Y
1$
#11625
0$
#11650
b110001010 X
b11000101 Y
1$
#11675
0$
#11700
b110001100 X
b11000110 Y
1$
#11725
0$
#11750
b110001110 X
b11000111 Y
1$
#11775
0$
#11800
b110010000 X
b11001000 Y
1$
#11825
0$
#11850
b110010010 X
b11001001 Y
1$
#11875
0$
#11900
b110010100 X
b11001010 Y
1$
#11925
0$
#11950
b110010110 X
b11001011 Y
1$
#11975
0$
#12000
b110011000 X
b11001100 Y
1$
#12025
0$
#12050
b110011010 X
b11001101 Y
1$
#12075
0$
#12100
b110011100 X
b11001110 Y
1$
#12125
0$
#12150
b110011110 X
b11001111 Y
1$
#12175
0$
#12200
b110100000 X
b11010000 Y
1$
#12225
0$
#12250
b110100010 X
b11010001 Y
1$
#12275
0$
#12300
b110100100 X
b11010010 Y
1$
#12325
0$
#12350
b110100110 X
b11010011 Y
1$
#12375
0$
#12400
b110101000 X
b11010100 Y
1$
#12425
0$
#12450
b110101010 X
b11010101 Y
1$
#12475
0$
#12500
b110101100 X
b11010110 Y
1$
#12525
0$
#12550
b110101110 X
b11010111 Y
1$
#12575
0$
#12600
b110110000 X
b11011000 Y
1$
#12625
0$
#12650
b110110010 X
b11011001 Y
1$
#12675
0$
#12700
b110110100 X
b11011010 Y
1$
#12725
0$
#12750
b110110110 X
b11011011 Y
1$
#12775
0$
#12800
b110111000 X
b11011100 Y
1$
#12825
0$
#12850
b110111010 X
b11011101 Y
1$
#12875
0$
#12900
b110111100 X
b11011110 Y
1$
#12925
0$
#12950
b110111110 X
b11011111 Y
1$
#12975
0$
#13000
b111000000 X
b11100000 Y
1$
#13025
0$
#13050
b111000010 X
b11100001 Y
1$
#13075
0$
#13100
b111000100 X
b11100010 Y
1$
#13125
0$
#13150
b111000110 X
b11100011 Y
1$
#13175
0$
#13200
b111001000 X
b11100100 Y
1$
#13225
0$
#13250
b111001010 X
b11100101 Y
1$
#13275
0$
#13300
b111001100 X
b11100110 Y
1$
#13325
0$
#13350
b111001110 X
b11100111 Y
1$
#13375
0$
#13400
b111010000 X
b11101000 Y
1$
#13425
0$
#13450
b111010010 X
b11101001 Y
1$
#13475
0$
#13500
b111010100 X
b11101010 Y
1$
#13525
0$
#13550
b111010110 X
b11101011 Y
1$
#13575
0$
#13600
b111011000 X
b11101100 Y
1$
#13625
0$
#13650
b111011010 X
b11101101 Y
1$
#13675
0$
#13700
b111011100 X
b11101110 Y
1$
#13725
0$
#13750
b111011110 X
b11101111 Y
1$
#13775
0$
#13800
b111100000 X
b11110000 Y
1$
#13825
0$
#13850
b111100010 X
b11110001 Y
1$
#13875
0$
#13900
b111100100 X
b11110010 Y
1$
#13925
0$
#13950
b111100110 X
b11110011 Y
1$
#13975
0$
#14000
b111101000 X
b11110100 Y
1$
#14025
0$
#14050
b111101010 X
b11110101 Y
1$
#14075
0$
#14100
b111101100 X
b11110110 Y
1$
#14125
0$
#14150
b111101110 X
b11110111 Y
1$
#14175
0$
#14200
b111110000 X
b11111000 Y
1$
#14225
0$
#14250
b111110010 X
b11111001 Y
1$
#14275
0$
#14300
b111110100 X
b11111010 Y
1$
#14325
0$
#14350
b111110110 X
b11111011 Y
1$
#14375
0$
#14400
b111111000 X
b11111100 Y
1$
#14425
0$
#14450
b111111010 X
b11111101 Y
1$
#14475
0$
#14500
b111111100 X
b11111110 Y
1$
#14525
0$
#14550
b111111110 X
b11111111 Y
1$
#14575
0$
#14600
b1000000000 X
b100000000 Y
1$
#14625
0$
#14650
b1000000010 X
b100000001 Y
1$
#14675
0$
#14700
b1000000100 X
b100000010 Y
1$
#14725
0$
