verilog/wbuf_pool/wbuf_send_pool.v
module wbuf_send_pool(
	input wire CLK, 
	input wire RSTL,
	input wire WBUF_SEND_POOL, //開始スイッチ
	input wire [15:0] addr, //SRAMの開始アドレス
	input wire [15:0] loop, //ループ回数
  input wire [7:0] sharp, //#の個数
	input wire [5:0] wbuf_ec, //PBの列指定
	output reg [2:0] cnt, //#のサイクル(4周期)
	output reg [7:0] cnt_sharp, //#用カウンター
	output reg [3:0] cnt_loop, //ループ中のサイクル(8周期)
	output reg [15:0] RADDRX, //_WEの処理の数値
	output reg RCEBX, //データを取り出す処理
	output reg WBUF_EN, //1：PB受け入れ開始
	output reg [5:0] WBUF_EN_CTRL, //PBの列指定
	output reg [15:0] COUNTER0, //ループ回数
	output reg WBUF_PURGE, //0:MAC演算機（PBに備えついている）のレジスタをリセット
	output reg I_COMPARE_MODE, //縦二つのデータを比較するモード
	output reg I_COMPARE_REGEN, //１：SRAMから比較機へのデータ転送開始(現在のアドレスの値を転送)
	output reg I_COMPARE_SWITCH, //比較機のレジスタを切り替え(アドレスが４進んだ時点で切り替え)
	output reg I_COMPARE_EN //比較機で比較して大きい方のデータを返す
	);

	//#用カウンター
  always @(posedge CLK or negedge RSTL) begin
    if (!RSTL)			
			cnt_sharp <= 8'd0;
    else if(WBUF_SEND_POOL)
      cnt_sharp <= 8'd1;
    else if(cnt_sharp != sharp)
      cnt_sharp <= cnt_sharp + 1;
  end

  //ループの外用カウンター(4サイクル)
  always @(posedge CLK or negedge RSTL) begin
		if (!RSTL)			
			cnt <= 3'b000;
    else if(WBUF_SEND_POOL)
      cnt <= 3'b001;
    else if(cnt == 3'b100) begin
      if(cnt_sharp == sharp)
        cnt <= 3'b000;
      else
        cnt <= 3'b001;
    end
    else
      cnt <= cnt + 1;
	end

	//ループ用カウンター
  always @(posedge CLK or negedge RSTL)  begin
		if (!RSTL)			
			COUNTER0 <= 16'd0;
		else if(WBUF_SEND_POOL) begin
			COUNTER0 <= loop;
		end else if(COUNTER0 != 0 && cnt_loop == 4'b1000) //１ループを8サイクル設定
			COUNTER0 <= COUNTER0 - 1;
	end

	//ループの中身用カウンタ(8サイクル)
  always @(posedge CLK or negedge RSTL) begin
		if (!RSTL)			
			cnt_loop <= 4'b0000;
		else if(COUNTER0) begin
			if(cnt_loop == 4'b1000) begin
				if(COUNTER0 == 16'd1) begin
					cnt_loop <= 4'b0000;
					WBUF_EN <= 0;
				end else
					cnt_loop <= 4'b0001;
			end else
        cnt_loop <= cnt_loop + 1;
		end else
			cnt_loop <= 4'b0000;
	end

  //WBUF_PURGE
  always @(posedge CLK or negedge RSTL) begin
		if (!RSTL)			
			WBUF_PURGE <= 0;
		else if(WBUF_SEND_POOL)
			WBUF_PURGE <= 1;
    else if(I_COMPARE_MODE == 1)
			WBUF_PURGE <= 0;
	end

	//RADDRX
	always @(cnt) begin
		if (!RSTL)			
			RADDRX <= 16'd0;
		else if(WBUF_SEND_POOL)
			RADDRX <= addr;
    else if(RADDRX == 3)
      RADDRX <= RADDRX + 16'd125;
    else if(cnt_loop == 3)
      RADDRX <= RADDRX - 16'd127;
    else if(cnt_loop == 7)
      RADDRX <= RADDRX + 16'd125;
    else if(cnt_loop != 5 || cnt_loop != 6)
			RADDRX <= RADDRX + 16'd1;
	end

	//WBUF_EN_CTRL
	always@ (cnt) begin
		if (!RSTL)       
			WBUF_EN_CTRL <= 6'b0;
		else if(WBUF_SEND_POOL) 
			WBUF_EN_CTRL <= wbuf_ec;
		else if(cnt == 4'b0001)
			WBUF_EN_CTRL <= WBUF_EN_CTRL + 6'b1;
	end

  //I_COMPARE
  always@ (posedge CLK or negedge RSTL) begin
    if(!RSTL) begin
      I_COMPARE_MODE <= 0;
      I_COMPARE_REGEN <= 0;
      I_COMPARE_SWITCH <= 0;
      I_COMPARE_EN <= 0;
    end
    else if(WBUF_SEND_POOL)
      I_COMPARE_MODE <= 1;

  end


endmodule

verilog/wbuf_pool/wbuf_send_pool_test.v
module wbuf_send_pool_test;
  reg CLK, RSTL, WBUF_SEND_POOL;
  reg [15:0] addr;
  reg [15:0] loop;
  reg [7:0] sharp;
  reg [5:0] wbuf_ec;
  wire [2:0] cnt;
  wire [7:0] cnt_sharp;
  wire [3:0] cnt_loop;
  wire [15:0] RADDRX;
  wire [5:0] WBUF_EN_CTRL;
  wire [15:0] COUNTER0;
  wire WBUF_EN, RCEBX, WBUF_PURGE, I_COMPARE_MODE, I_COMPARE_REGEN, I_COMPARE_SWITCH, I_COMPARE_EN;

  wbuf_send_pool wbuf_send_pool_instance(
    .CLK(CLK),
    .RSTL(RSTL),
    .WBUF_SEND_POOL(WBUF_SEND_POOL),
    .addr(addr),
    .loop(loop),
    .sharp(sharp),
    .wbuf_ec(wbuf_ec),
    .cnt(cnt),
    .cnt_sharp(cnt_sharp),
    .cnt_loop(cnt_loop),
    .COUNTER0(COUNTER0),
    .RCEBX(RCEBX),
    .WBUF_EN(WBUF_EN),
    .WBUF_EN_CTRL(WBUF_EN_CTRL),
    .WBUF_PURGE(WBUF_PURGE),
    .I_COMPARE_MODE(I_COMPARE_MODE), 
    .I_COMPARE_REGEN(I_COMPARE_REGEN),
    .I_COMPARE_SWITCH(I_COMPARE_SWITCH),
    .I_COMPARE_EN(I_COMPARE_EN)
  );

  parameter step = 10;

  initial begin
    CLK = 0;
    forever #(step) CLK = ~CLK;
  end

  initial begin
    RSTL = 0;
    WBUF_SEND_POOL = 0;
    addr = 16'b0; //SRAMの開始アドレス
    wbuf_ec = 6'b0; //PBの開始列
    loop = 5; //ループ回数
    sharp = 27; //#の数

    #(step*3)
    RSTL = 1;
    WBUF_SEND_POOL = 1;

    #step
    WBUF_SEND_POOL = 0;
    I_COMPARE_MODE = 1;
    RCEBX = 0;

    #step
    I_COMPARE_REGEN = 1;

    #(step*2)

  end

  initial begin
    #(step*100) $finish();
  end
  
  initial begin
    $dumpfile("wbuf_send_pool_test.vcd");
    $dumpvars(0, wbuf_send_pool_instance);
  end

endmodule

verilog/wbuf_pool/wbuf_send_pool_test.vcd
$date
	Wed Oct 28 16:38:10 2020
$end
$version
	Icarus Verilog
$end
$timescale
	1s
$end
$scope module wbuf_send_pool_test $end
$scope module wbuf_send_pool_instance $end
$var wire 1 ! CLK $end
$var wire 1 " RSTL $end
$var wire 1 # WBUF_SEND_POOL $end
$var wire 16 $ addr [15:0] $end
$var wire 16 % loop [15:0] $end
$var wire 8 & sharp [7:0] $end
$var wire 6 ' wbuf_ec [5:0] $end
$var reg 16 ( COUNTER0 [15:0] $end
$var reg 1 ) I_COMPARE_EN $end
$var reg 1 * I_COMPARE_MODE $end
$var reg 1 + I_COMPARE_REGEN $end
$var reg 1 , I_COMPARE_SWITCH $end
$var reg 16 - RADDRX [15:0] $end
$var reg 1 . RCEBX $end
$var reg 1 / WBUF_EN $end
$var reg 6 0 WBUF_EN_CTRL [5:0] $end
$var reg 1 1 WBUF_PURGE $end
$var reg 3 2 cnt [2:0] $end
$var reg 4 3 cnt_loop [3:0] $end
$var reg 8 4 cnt_sharp [7:0] $end
$upscope $end
$upscope $end
$enddefinitions $end
#0
$dumpvars
b0 4
b0 3
b0 2
x1
b0 0
x/
x.
b0 -
0,
0+
0*
0)
b0 (
b0 '
b11011 &
b101 %
b0 $
0#
0"
0!
$end
#10
1!
#20
0!
#30
b1 4
b1 2
b101 (
1*
1!
1#
1"
#40
0!
0#
#50
b1 -
b1 3
b10 2
b10 4
1!
#60
0!
#70
b10 -
b11 4
b11 2
b10 3
1!
#80
0!
#90
b11 -
b11 3
b100 2
b100 4
1!
#100
0!
#110
b100 -
b1 0
b101 4
b1 2
b100 3
1!
#120
0!
#130
b101 -
b101 3
b10 2
b110 4
1!
#140
0!
#150
b110 -
b111 4
b11 2
b110 3
1!
#160
0!
#170
b111 -
b111 3
b100 2
b1000 4
1!
#180
0!
#190
b1000 -
b10 0
b1001 4
b1 2
b1000 3
1!
#200
0!
#210
b1001 -
b1 3
b100 (
b10 2
b1010 4
1!
#220
0!
#230
b1010 -
b1011 4
b11 2
b10 3
1!
#240
0!
#250
b1011 -
b11 3
b100 2
b1100 4
1!
#260
0!
#270
b1100 -
b11 0
b1101 4
b1 2
b100 3
1!
#280
0!
#290
b1101 -
b101 3
b10 2
b1110 4
1!
#300
0!
#310
b1110 -
b1111 4
b11 2
b110 3
1!
#320
0!
#330
b1111 -
b111 3
b100 2
b10000 4
1!
#340
0!
#350
b10000 -
b100 0
b10001 4
b1 2
b1000 3
1!
#360
0!
#370
b10001 -
b1 3
b11 (
b10 2
b10010 4
1!
#380
0!
#390
b10010 -
b10011 4
b11 2
b10 3
1!
#400
0!
#410
b10011 -
b11 3
b100 2
b10100 4
1!
#420
0!
#430
b10100 -
b101 0
b10101 4
b1 2
b100 3
1!
#440
0!
#450
b10101 -
b101 3
b10 2
b10110 4
1!
#460
0!
#470
b10110 -
b10111 4
b11 2
b110 3
1!
#480
0!
#490
b10111 -
b111 3
b100 2
b11000 4
1!
#500
0!
#510
b11000 -
b110 0
b11001 4
b1 2
b1000 3
1!
#520
0!
#530
b11001 -
b1 3
b10 (
b10 2
b11010 4
1!
#540
0!
#550
b11010 -
b11011 4
b11 2
b10 3
1!
#560
0!
#570
b11011 -
b11 3
b100 2
1!
#580
0!
#590
b11100 -
b0 2
b100 3
1!
#600
0!
#610
b111 0
b11101 -
b101 3
b1 2
1!
#620
0!
#630
b11110 -
b10 2
b110 3
1!
#640
0!
#650
b11111 -
b111 3
b11 2
1!
#660
0!
#670
b100000 -
b100 2
b1000 3
1!
#680
0!
#690
b100001 -
b1 3
b1 (
b0 2
1!
#700
0!
#710
b100010 -
b1000 0
b1 2
b10 3
1!
#720
0!
#730
b100011 -
b11 3
b10 2
1!
#740
0!
#750
b100100 -
b11 2
b100 3
1!
#760
0!
#770
b100101 -
b101 3
b100 2
1!
#780
0!
#790
b100110 -
b0 2
b110 3
1!
#800
0!
#810
b1001 0
b100111 -
b111 3
b1 2
1!
#820
0!
#830
b101000 -
b10 2
b1000 3
1!
#840
0!
#850
b101001 -
0/
b0 3
b0 (
b11 2
1!
#860
0!
#870
b101010 -
b100 2
1!
#880
0!
#890
b101011 -
b0 2
1!
#900
0!
#910
b101100 -
b1010 0
b1 2
1!
#920
0!
#930
b101101 -
b10 2
1!
#940
0!
#950
b101110 -
b11 2
1!
#960
0!
#970
b101111 -
b100 2
1!
#980
0!
#990
b110000 -
b0 2
1!
