verilog/output/output_send.v
module output_send(
	input wire CLK, 
	input wire RSTL,
	input wire OUTPUT_SEND, //開始スイッチ
	input wire [15:0] addr, //SRAMの開始アドレス
	input wire [15:0] loop, //ループ回数
	input wire [5:0] output_ec, //PBの列指定
	input wire [15:0] pc, //プログラムカウンタ
	output reg [2:0] cnt, //#のサイクル(4周期)
	output reg [15:0] WADDRX, //_WEの処理の数値
	output reg WCEBX, //データを取り出す処理
	output reg OUTPUT_EN, //0：PB受け入れ中止, 1：PB受け入れ開始
	output reg [5:0] OUTPUT_EN_CTRL, //PBの列指定
	output reg [15:0] COUNTER0 //ループ回数
	);


	// pc
	// always @(posedge CLK or negedge RSTL)  begin
	// 	if (!RSTL)			
	// 		pc <= 16'd0;
	// 	else if(OUTPUT_SEND)
	// 		pc <= pc + 16'd1;
	// end
	
	//ループ用カウンター
  always @(posedge CLK or negedge RSTL)  begin
		if (!RSTL) begin
			COUNTER0 <= 16'd0;
			WCEBX <= 1;
			OUTPUT_EN <= 0;
		end else if(OUTPUT_SEND) begin
			COUNTER0 <= loop;
			WCEBX <= 0;
			OUTPUT_EN <= 1;
		end else if(COUNTER0 != 0 && cnt == 3'b100) //１ループを4サイクル設定
			COUNTER0 <= COUNTER0 - 1;
	end

	//ループの中身用カウンタ(4サイクル)
  always @(posedge CLK or negedge RSTL) begin
		if (!RSTL)			
			cnt <= 3'b000;
		else if(COUNTER0) begin
			if(cnt == 3'b100) begin
				if(COUNTER0 == 16'd1) begin
					cnt <= 3'b000;
					OUTPUT_EN <= 0;
				end else
					cnt <= 3'b001;
			end else
        cnt <= cnt + 1;
		end else
			cnt <= 3'b000;
	end

	//WADDRX
	always @(cnt) begin
		if (!RSTL)			
			WADDRX <= 16'd0;
		else if(OUTPUT_SEND)
			WADDRX <= addr;
		else if(COUNTER0)
			if(COUNTER0 != loop || cnt != 3'b001)
				WADDRX <= WADDRX + 16'd1;
	end

	//OUTPUT_EN_CTRL
	always@ (cnt) begin
		if (!RSTL)       
			OUTPUT_EN_CTRL <= 6'b0;
		else if(OUTPUT_SEND) 
			OUTPUT_EN_CTRL <= output_ec;
		else if(cnt == 3'b001)
			OUTPUT_EN_CTRL <= OUTPUT_EN_CTRL + 6'b1;
	end


endmodule

verilog/output/output_send_test.v
module output_send_test;
  reg CLK, RSTL, OUTPUT_SEND;
  reg [15:0] addr;
  reg [15:0] loop;
  reg [5:0] output_ec;
  reg [15:0] pc;
  wire [2:0] cnt;
  wire [15:0] WADDRX;
  wire [5:0] OUTPUT_EN_CTRL;
  wire [15:0] COUNTER0;
  wire OUTPUT_EN, WCEBX;

  output_send output_send_instance(
    .CLK(CLK),
    .RSTL(RSTL),
    .OUTPUT_SEND(OUTPUT_SEND),
    .addr(addr),
    .loop(loop),
    .pc(pc),
    .output_ec(output_ec),
    .cnt(cnt),
    .WADDRX(WADDRX),
    .COUNTER0(COUNTER0),
    .WCEBX(WCEBX),
    .OUTPUT_EN(OUTPUT_EN),
    .OUTPUT_EN_CTRL(OUTPUT_EN_CTRL)
  );

  parameter step = 10;

  initial begin
    CLK = 0;
    forever #(step) CLK = ~CLK;
  end

  initial begin
    pc = 0;
    #(step*3)
    forever #(step*2) pc = pc + 1;
  end

  initial begin
    RSTL = 0;
    OUTPUT_SEND = 0;
    addr = 16'd0; //SRAMの開始アドレス
    output_ec = 6'd0; //PBの開始列
    loop = 5; //ループ回数
    #(step*3)
    RSTL = 1;
    OUTPUT_SEND = 1;

    #step
    OUTPUT_SEND = 0;
  end

  // initial begin
  //   #(step*45) 
  //   OUTPUT_SEND = 1;
  //   #step
  //   OUTPUT_SEND = 0;
  // end

  initial begin
    #(step*100) $finish();
  end
  
  initial begin
    $dumpfile("output_send_test.vcd");
    $dumpvars(0, output_send_instance);
  end

endmodule

verilog/output/output_send_test.vcd
$date
	Wed Nov 18 15:04:22 2020
$end
$version
	Icarus Verilog
$end
$timescale
	1s
$end
$scope module output_send_test $end
$scope module output_send_instance $end
$var wire 1 ! CLK $end
$var wire 1 " OUTPUT_SEND $end
$var wire 1 # RSTL $end
$var wire 16 $ addr [15:0] $end
$var wire 16 % loop [15:0] $end
$var wire 6 & output_ec [5:0] $end
$var wire 16 ' pc [15:0] $end
$var reg 16 ( COUNTER0 [15:0] $end
$var reg 1 ) OUTPUT_EN $end
$var reg 6 * OUTPUT_EN_CTRL [5:0] $end
$var reg 16 + WADDRX [15:0] $end
$var reg 1 , WCEBX $end
$var reg 3 - cnt [2:0] $end
$upscope $end
$upscope $end
$enddefinitions $end
#0
$dumpvars
b0 -
1,
b0 +
b0 *
0)
b0 (
b0 '
b0 &
b101 %
b0 $
0#
0"
0!
$end
#10
1!
#20
0!
#30
1)
0,
b101 (
1!
1"
1#
#40
0!
0"
#50
b1 *
b1 -
1!
b1 '
#60
0!
#70
b1 +
b10 -
1!
b10 '
#80
0!
#90
b10 +
b11 -
1!
b11 '
#100
0!
#110
b11 +
b100 -
1!
b100 '
#120
0!
#130
b100 +
b10 *
b1 -
b100 (
1!
b101 '
#140
0!
#150
b101 +
b10 -
1!
b110 '
#160
0!
#170
b110 +
b11 -
1!
b111 '
#180
0!
#190
b111 +
b100 -
1!
b1000 '
#200
0!
#210
b1000 +
b11 *
b1 -
b11 (
1!
b1001 '
#220
0!
#230
b1001 +
b10 -
1!
b1010 '
#240
0!
#250
b1010 +
b11 -
1!
b1011 '
#260
0!
#270
b1011 +
b100 -
1!
b1100 '
#280
0!
#290
b1100 +
b100 *
b1 -
b10 (
1!
b1101 '
#300
0!
#310
b1101 +
b10 -
1!
b1110 '
#320
0!
#330
b1110 +
b11 -
1!
b1111 '
#340
0!
#350
b1111 +
b100 -
1!
b10000 '
#360
0!
#370
b10000 +
b101 *
b1 -
b1 (
1!
b10001 '
#380
0!
#390
b10001 +
b10 -
1!
b10010 '
#400
0!
#410
b10010 +
b11 -
1!
b10011 '
#420
0!
#430
b10011 +
b100 -
1!
b10100 '
#440
0!
#450
0)
b0 -
b0 (
1!
b10101 '
#460
0!
#470
1!
b10110 '
#480
0!
#490
1!
b10111 '
#500
0!
#510
1!
b11000 '
#520
0!
#530
1!
b11001 '
#540
0!
#550
1!
b11010 '
#560
0!
#570
1!
b11011 '
#580
0!
#590
1!
b11100 '
#600
0!
#610
1!
b11101 '
#620
0!
#630
1!
b11110 '
#640
0!
#650
1!
b11111 '
#660
0!
#670
1!
b100000 '
#680
0!
#690
1!
b100001 '
#700
0!
#710
1!
b100010 '
#720
0!
#730
1!
b100011 '
#740
0!
#750
1!
b100100 '
#760
0!
#770
1!
b100101 '
#780
0!
#790
1!
b100110 '
#800
0!
#810
1!
b100111 '
#820
0!
#830
1!
b101000 '
#840
0!
#850
1!
b101001 '
#860
0!
#870
1!
b101010 '
#880
0!
#890
1!
b101011 '
#900
0!
#910
1!
b101100 '
#920
0!
#930
1!
b101101 '
#940
0!
#950
1!
b101110 '
#960
0!
#970
1!
b101111 '
#980
0!
#990
1!
b110000 '
