verilog/cal/conv_cal.v
module conv_cal(
	input wire CLK, 
	input wire RSTL,
	input wire CONV_CAL, //開始スイッチ
	//input wire [15:0] addr, //SRAMの開始アドレス
	input wire [15:0] loop, //ループ回数
	//input wire [5:0] wbuf_ec, //PBの列指定
	output reg [2:0] cnt, //#のサイクル(5サイクル)
	output reg [15:0] RADDRW, //SRAMの重みを読み込み
	output reg RCEBW, //0:重みを読み込む処理
	//output reg WBUF_EN, //0：PB受け入れ中止, 1：PB受け入れ開始
	//output reg [5:0] WBUF_EN_CTRL, //PBの列指定
	output reg [15:0] COUNTER0, //ループ回数
  output reg NL_EN, //PBの値をずらす(4サイクル後にずれる)
  output reg MAC_EN //MAC演算を行う(畳み込む)
	);

	
	//COUNTER0:ループ回数用カウンター
  always @(posedge CLK or negedge RSTL)  begin
		if (!RSTL)			
			COUNTER0 <= 16'd0;
		else if(CONV_CAL) begin
			COUNTER0 <= loop;
		end else if(cnt == 3'b101) //１ループを4サイクル設定
			COUNTER0 <= COUNTER0 - 1;
	end

	//cnt:ループの中身用カウンタ(5サイクル)
  always @(posedge CLK or negedge RSTL) begin
		if (!RSTL)			
			cnt <= 3'b000;
		else if(COUNTER0) begin
			if(cnt == 3'b101) begin
				if(COUNTER0 == 16'd1) begin
					cnt <= 3'b000;
				end else
					cnt <= 3'b001;
			end else
        cnt <= cnt + 1;
		end else
			cnt <= 3'b000;
	end

	//RADDRW
	always @(posedge CLK or negedge RSTL) begin
		if (!RSTL)			
			RADDRW <= 16'd0;
    else if(CONV_CAL)
      RADDRW <= 16'd0;
		else if(COUNTER0)
      if(cnt != 3'b101 || COUNTER0 != 1) //!が入ると||は&&になるっぽい
			  if(cnt == 3'b011)
          RADDRW <= RADDRW;
        else
          RADDRW <= RADDRW + 16'd1;
	end

  //RCEBW
	always @(posedge CLK or negedge RSTL) begin
		if (!RSTL)			
			RCEBW <= 1;
		else if(CONV_CAL)
			RCEBW <= 0;
		else if(cnt == 3'b101 && COUNTER0 == 1)
			RCEBW <= 1;
	end

	//NL_EN
	always@ (posedge CLK or negedge RSTL) begin
		if (!RSTL)       
			NL_EN <= 0;
		else if(COUNTER0) begin
      if(cnt == 3'b100)
        NL_EN <= 0;
      else if(COUNTER0 == 1 && cnt == 3'b101)
        NL_EN <= 0;
      else
        NL_EN <= 1;
    end else
      NL_EN <= 0;
	end

  //MAC_EN
	always@ (posedge CLK or negedge RSTL) begin
		if (!RSTL)       
			MAC_EN <= 0;
    else if(COUNTER0) begin
      if(cnt == 3'b001 || cnt == 3'b010 || cnt == 3'b011 || cnt == 3'b100)
        MAC_EN <= 0;
      else if(cnt == 3'b101 && COUNTER0 == 1)
        MAC_EN <= 0;
      else
        MAC_EN <= 1;
    end
	end


endmodule

verilog/cal/conv_cal_test.v
module conv_cal_test;
  reg CLK, RSTL, CONV_CAL;
  reg [15:0] loop;
  wire [2:0] cnt;
  wire [15:0] RADDRW;
  wire [15:0] COUNTER0;
  wire RCEBW, NL_EN, MAC_EN;

  conv_cal conv_cal_instance(
    .CLK(CLK),
    .RSTL(RSTL),
    .CONV_CAL(CONV_CAL),
    .loop(loop),
    .cnt(cnt),
    .RADDRW(RADDRW),
    .COUNTER0(COUNTER0),
    .RCEBW(RCEBW),
    .NL_EN(NL_EN),
    .MAC_EN(MAC_EN)
  );

  parameter step = 10;

  initial begin
    CLK = 0;
    forever #(step) CLK = ~CLK;
  end

  initial begin
    RSTL = 0;
    CONV_CAL = 0;
    loop = 5; //ループ回数
    #(step*3)
    RSTL = 1;
    CONV_CAL = 1;
    #step
    CONV_CAL = 0;

    // #(step*53)
    // CONV_CAL = 1;
    // #step
    // CONV_CAL = 0;
  end

  initial begin
    #(step*100) $finish();
  end
  
  initial begin
    $dumpfile("conv_cal_test.vcd");
    $dumpvars(0, conv_cal_instance);
  end

endmodule

verilog/cal/conv_cal_test.vcd
$date
	Wed Nov 18 16:03:24 2020
$end
$version
	Icarus Verilog
$end
$timescale
	1s
$end
$scope module conv_cal_test $end
$scope module conv_cal_instance $end
$var wire 1 ! CLK $end
$var wire 1 " CONV_CAL $end
$var wire 1 # RSTL $end
$var wire 16 $ loop [15:0] $end
$var reg 16 % COUNTER0 [15:0] $end
$var reg 1 & MAC_EN $end
$var reg 1 ' NL_EN $end
$var reg 16 ( RADDRW [15:0] $end
$var reg 1 ) RCEBW $end
$var reg 3 * cnt [2:0] $end
$upscope $end
$upscope $end
$enddefinitions $end
#0
$dumpvars
b0 *
1)
b0 (
0'
0&
b0 %
b101 $
0#
0"
0!
$end
#10
1!
#20
0!
#30
b101 %
0)
1!
1"
1#
#40
0!
0"
#50
1&
1'
b1 (
b1 *
1!
#60
0!
#70
b10 *
b10 (
0&
1!
#80
0!
#90
b11 (
b11 *
1!
#100
0!
#110
b100 *
1!
#120
0!
#130
0'
b100 (
b101 *
1!
#140
0!
#150
b100 %
b1 *
b101 (
1'
1&
1!
#160
0!
#170
0&
b110 (
b10 *
1!
#180
0!
#190
b11 *
b111 (
1!
#200
0!
#210
b100 *
1!
#220
0!
#230
b101 *
b1000 (
0'
1!
#240
0!
#250
1&
1'
b1001 (
b1 *
b11 %
1!
#260
0!
#270
b10 *
b1010 (
0&
1!
#280
0!
#290
b1011 (
b11 *
1!
#300
0!
#310
b100 *
1!
#320
0!
#330
0'
b1100 (
b101 *
1!
#340
0!
#350
b10 %
b1 *
b1101 (
1'
1&
1!
#360
0!
#370
0&
b1110 (
b10 *
1!
#380
0!
#390
b11 *
b1111 (
1!
#400
0!
#410
b100 *
1!
#420
0!
#430
b101 *
b10000 (
0'
1!
#440
0!
#450
1&
1'
b10001 (
b1 *
b1 %
1!
#460
0!
#470
b10 *
b10010 (
0&
1!
#480
0!
#490
b10011 (
b11 *
1!
#500
0!
#510
b100 *
1!
#520
0!
#530
0'
b10100 (
b101 *
1!
#540
0!
#550
b0 %
b0 *
1)
1!
